Workbook

Sheet Start Here
A1: Grapevine Editorial Base — Excel Starter | F1: Quick KPIs | G1: Quick KPIs | H1: Quick KPIs
A2: Purpose | B2: Starter workbook for your editorial base library, source register, pattern register, thesis register, and update governance. | F2: Starter docs | G2: =COUNTA(Library_Master!A2:A68) -> 67
A3: How to use | B3: 1) Start in Library_Master. 2) Keep controlled fields consistent via the dropdowns. 3) Use Source_Register before adding new sources. 4) Review due items weekly. | F3: Core assets | G3: =COUNTIF(Library_Master!AS2:AS68,TRUE) -> 57
A4: Included tabs | B4: Start Here, Library_Master (incl. Asset Class), Source_Register, Pattern_Register, Thesis_Register, Update_Timetable, Controlled_Values | F4: Evergreen refs | G4: =COUNTIF(Library_Master!AT2:AT68,TRUE) -> 24
A5: Status logic | B5: backlog → triage → validated → converted/published → archived | F5: Internal / mixed assets | G5: =COUNTIFS(Library_Master!G2:G68,"internal")+COUNTIFS(Library_Master!G2:G68,"mixed")+COUNTIFS(Library_Master!G2:G68,"derived") -> 39
A6: Scoring | B6: Editorial Value, Commercial Value, Reuse Potential are 1–5. Value Score auto-sums them. | F6: High priority items | G6: =COUNTIF(Library_Master!AA2:AA68,"high") -> 43
A7: Review logic | B7: Review Due flags items whose Next Review Date is due or overdue. | F7: Proprietary % | G7: =COUNTIF(Library_Master!AW2:AW68,"proprietary")/COUNTA(Library_Master!A2:A68) -> 0.55223881
A8: Owner tip | B8: Use one owner per row to avoid accountability drift. | F8: Patterns registered | G8: =COUNTA(Pattern_Register!A2:A100) -> 8
F9: Theses registered | G9: =COUNTA(Thesis_Register!A2:A100) -> 4
F10: Knowledge Cards | G10: =COUNTA(Knowledge_Cards!A2:A100) -> 10
F11: Items due for review | G11: =COUNTIF(Library_Master!AV2:AV68,TRUE) -> 0
A12: Asset Classification
A13: Commodity | B13: Everyone has it. Bain, McKinsey, IMF. Provides credibility but zero differentiation.
A14: Contextual | B14: You reframe it with your own lens. Sector overlays, Benelux angle, V4G interpretation. Creates conversation edge.
A15: Proprietary | B15: Only you have it. Internal memos, failure patterns, deal signals, casenotes. This is your moat.
A17: Naming Convention
A18: File name format | B18: ka_[type]_[Source]_[Topic]_[Geography]_[Year]_v[version]
A19: Example | B19: ka_benchmark_Bain_Global_PE_Global_2025_v1
A20: ID format | B20: EBL-0001 through EBL-9999 (sequential, never reused)
A22: KA Types Reference
A23: ka_benchmark | B23: External market reports & indices (quarterly/annual)
A24: ka_market_map | B24: Sector heatmaps & consolidation views (quarterly)
A25: ka_framework | B25: Canonical reference frameworks (annual)
A26: ka_pattern | B26: Recurring behavioral/execution patterns (monthly)
A27: ka_failure_pattern | B27: Deal failure analysis & prevention (monthly)
A28: ka_thesis | B28: Investment/editorial theses (quarterly)
A29: ka_editorial_angle | B29: Publishable content angles (weekly)
A30: ka_signal_digest | B30: Weak signal tracking & alerts (weekly)
A31: ka_internal_standard | B31: House views & internal norms (quarterly)
A32: ka_library_source | B32: Macro/reference library sources (annual)
A35: How It All Fits Together
A37: The Intelligence Pipeline
A38: This system converts raw documents into deal intelligence through 5 stages:
A40: Stage 1 — Docs | B40: Library_Master holds every document: reports, memos, datasets, checklists. Each tagged with metadata (source, sector, geography, freshness). This is inventory, not intelligence.
A41: Stage 2 — Cards | B41: Knowledge_Cards distills each doc into a usable insight: Key Insight → Data Points → So What? → Use In Conversation. A card is what you carry into a meeting — not the report, but the 4 things from it that matter.
A42: Stage 3 — Patterns | B42: Pattern_Register captures recurring behaviors across deals: founders hesitating, buyers withdrawing, friction points. Patterns emerge from multiple cards and observations. They are your predictive edge.
A43: Stage 4 — Theses | B43: Thesis_Register holds testable claims built on patterns and data: 'deal failures are predictable', 'signal convergence predicts activity'. Theses drive editorial content and advisory positioning.
A44: Stage 5 — Deals | B44: The end state: intelligence deployed in real conversations, pitches, and publications. A card used in a founder meeting. A pattern cited in a Dealflow.news article. A thesis tested against a live process.
A46: The 8 Sheets — What Lives Where
A48: Sheet | B48: Purpose
A49: 🏠 Start Here | B49: This page. System documentation, KPIs, reference tables. Your landing page.
A50: 📚 Library_Master | B50: All 67 documents with 49 metadata fields. The inventory. Filter by category, priority, asset class, owner. Stage 1.
A51: 🃏 Knowledge_Cards | B51: Distilled intelligence from docs. Each card has 4 layers: Key Insight → Data Points → So What → Use In Conversation. Stage 2.
A52: 📖 Source_Register | B52: 25 verified sources with reliability, access type, and coverage. Check here before adding a new source to the library.
A53: 📋 Pattern_Register | B53: 8 recurring deal patterns (failure, behavioral, execution, strategic). Linked to evidence and theses. Your predictive edge. Stage 3.
A54: 💡 Thesis_Register | B54: 4 testable claims built on pattern evidence. Drive editorial content and advisory positioning. Stage 4.
A55: ⏱️ Update_Timetable | B55: 10 ka_types with review cadence (weekly → annual), ownership, and trigger rules. The governance engine.
A56: 🏛️ Controlled_Values | B56: 24 dropdown lists that enforce consistent tagging across all sheets. The data quality backbone.
A58: How Things Connect
A59: Every item links to others. Here's how to read the connections:
A61: Connection | B61: How it works
A62: Doc → Card | B62: Knowledge_Cards.Source EBL links back to Library_Master.Short ID. One doc can produce multiple cards. When converted, the doc's Editorial Status changes to 'converted'.
A63: Card → Pattern | B63: Knowledge_Cards.Linked Patterns references Pattern_Register entries. Multiple cards can support the same pattern. Patterns strengthen as more cards confirm them.
A64: Pattern → Thesis | B64: Pattern_Register entries feed into Thesis_Register claims. A thesis is 'testable' when it has 2+ supporting patterns. It becomes 'validated' when confirmed by live deal data.
A65: Doc → Source | B65: Library_Master.Source must exist in Source_Register. Always check Source_Register before creating a new library entry. This prevents source proliferation.
A66: Everything → Timetable | B66: Every item's KA Type determines its review cadence via Update_Timetable. When Next Review Date passes, Review Due flags it. Weekly governance: check flagged items first.
A68: Your Weekly Workflow
A70: Day | B70: Action
A71: Monday | B71: Review flagged items (Items due for review KPI). Update signal digests. Check editorial angles for Dealflow.news.
A72: Wednesday | B72: Convert 1-2 high-priority docs into Knowledge Cards. Link new cards to existing patterns. Ask: does this confirm or challenge a thesis?
A73: Friday | B73: Quick KPI check on Start Here. Archive stale signals. Note any new pattern observations from the week's deal activity.
A74: Monthly | B74: Validate patterns (monthly cadence items). Review failure patterns against recent deal outcomes. Update benchmarks if new editions published.
A75: Quarterly | B75: Reassess all theses. Update market maps and sector heatmaps. Check Asset Class balance (target: >50% proprietary). Purge or archive obsolete items.
A77: The Strategic Insight
A78: Your competitive advantage is not having information — everyone can download Bain and McKinsey reports. Your advantage is the conversion speed from document to actionable deal intelligence. The faster you turn a market report into a Knowledge Card, link it to a pattern, and test it against a thesis, the wider your moat becomes. That's why this system exists.

Sheet Library_Master
A1: Short ID | B1: Title | C1: File Name | D1: KA Type | E1: Library Category | F1: Source | G1: Source Type | H1: Asset Format | I1: Sector | J1: Geography | K1: Company Relevance | L1: Theme | M1: Publication Date | N1: Ingest Date | O1: Last Reviewed | P1: Update Cadence | Q1: Next Review Date | R1: Freshness Class | S1: Time Sensitivity | T1: Confidence | U1: Evidence Status | V1: Editorial Value | W1: Commercial Value | X1: Reuse Potential | Y1: Value Score | Z1: Novelty | AA1: Priority | AB1: Editorial Status | AC1: Conversion Target | AD1: Ready for Conversion | AE1: Publishing Relevance | AF1: Sensitivity | AG1: Owner | AH1: Reviewer | AI1: Linked Patterns | AJ1: Linked Theses | AK1: External URL | AL1: Storage Status | AM1: Executive Summary | AN1: Why It Matters | AO1: Editorial Angle Notes | AP1: Commercial Use Notes | AQ1: Gaps / Follow-Up Needed | AR1: Starter Pack 50 | AS1: Core Asset | AT1: Evergreen | AU1: Obsolete Risk | AV1: Review Due | AW1: Asset Class
A2: EBL-0001 | B2: Bain Global Private Equity Report 2025 | C2: ka_benchmark_Bain_Global_PE_Global_2025_v1 | D2: ka_benchmark | E2: Core Market | F2: Bain & Company | G2: external | H2: pdf | I2: Cross-Sector | J2: Global; Europe | K2: PE-backed; Corporate Buyer | L2: Private Equity; Valuation; Macro Context | M2: 45717 | N2: 46128 | O2: 46128 | P2: annual | Q2: 46493 | R2: recent | S2: medium | T2: high | U2: multi_source | V2: 5 | W2: 4 | X2: 5 | Y2: =V2+W2+X2 -> 14 | Z2: contextual | AA2: high | AB2: converted | AC2: Knowledge Card; Thesis | AD2: TRUE | AE2: high | AF2: public | AG2: Editor | AK2: https://www.bain.com/ | AL2: linked | AM2: Annual PE benchmark report for cycle, dry powder, multiples and exits. | AN2: Citation backbone for market framing and PE logic. | AO2: PE climate, exit environment, pricing pressure. | AP2: Useful in founder and buyer conversations. | AQ2: Add prior-year comparison note | AR2: TRUE | AS2: TRUE | AT2: FALSE | AU2: low | AV2: =IF(AND(Q2<>"",Q2<=TODAY()),"Due","") | AW2: commodity
A3: EBL-0002 | B3: Bain Global Private Equity Report 2024 | C3: ka_benchmark_Bain_Global_PE_Global_2024_v1 | D3: ka_benchmark | E3: Core Market | F3: Bain & Company | G3: external | H3: pdf | I3: Cross-Sector | J3: Global; Europe | K3: PE-backed; Corporate Buyer | L3: Private Equity; Valuation; Macro Context | M3: 45352 | N3: 46128 | O3: 46128 | P3: annual | Q3: 46493 | R3: reference | S3: timeless | T3: high | U3: multi_source | V3: 4 | W3: 3 | X3: 4 | Y3: =V3+W3+X3 -> 11 | Z3: known_pattern | AA3: medium | AB3: validated | AC3: Knowledge Card | AD3: FALSE | AE3: medium | AF3: public | AG3: Editor | AK3: https://www.bain.com/ | AL3: linked | AM3: Prior-year PE benchmark for comparison. | AN3: Useful for trend comparison against latest edition. | AO3: Year-over-year context for market shifts. | AP3: Reference in longitudinal analysis. | AQ3: Check delta vs 2025 | AR3: TRUE | AS3: FALSE | AT3: FALSE | AU3: low | AV3: =IF(AND(Q3<>"",Q3<=TODAY()),"Due","") | AW3: commodity
A4: EBL-0003 | B4: PitchBook European PE & M&A Outlook | C4: ka_benchmark_PitchBook_European_PE_MA_Europe_2026_v1 | D4: ka_benchmark | E4: Core Market | F4: PitchBook | G4: external | H4: pdf | I4: Cross-Sector | J4: Europe | K4: PE-backed; Corporate Buyer | L4: Private Equity; Valuation; Deal Execution | M4: 46037 | N4: 46128 | O4: 46128 | P4: quarterly | Q4: 46219 | R4: recent | S4: medium | T4: high | U4: multi_source | V4: 5 | W4: 5 | X4: 5 | Y4: =V4+W4+X4 -> 15 | Z4: contextual | AA4: high | AB4: validated | AC4: Knowledge Card; Thesis | AD4: TRUE | AE4: high | AF4: restricted | AG4: Analyst | AK4: https://pitchbook.com/ | AL4: linked | AM4: European dealflow, exits and valuation outlook. | AN4: Important for Europe-specific pricing and timing narratives. | AO4: Use for pressure on exits and buyer behavior. | AP4: Strong for mandate conversations. | AQ4: Add subscription storage copy | AR4: TRUE | AS4: TRUE | AT4: FALSE | AU4: low | AV4: =IF(AND(Q4<>"",Q4<=TODAY()),"Due","") | AW4: commodity
A5: EBL-0004 | B5: PitchBook Valuations Report | C5: ka_benchmark_PitchBook_Valuations_Global_2026_v1 | D5: ka_benchmark | E5: Core Market | F5: PitchBook | G5: external | H5: pdf | I5: Cross-Sector | J5: Global | K5: PE-backed; Corporate Buyer | L5: Valuation; Private Equity | M5: 46037 | N5: 46128 | O5: 46128 | P5: quarterly | Q5: 46219 | R5: recent | S5: medium | T5: high | U5: multi_source | V5: 5 | W5: 4 | X5: 4 | Y5: =V5+W5+X5 -> 13 | Z5: contextual | AA5: high | AB5: triage | AC5: Knowledge Card | AD5: FALSE | AE5: medium | AF5: restricted | AG5: Analyst | AK5: https://pitchbook.com/ | AL5: linked | AM5: Valuation trends with broader market context. | AN5: Useful to triangulate pricing narratives. | AO5: Can support EV/EBITDA context pieces. | AP5: Useful in buyer valuation framing. | AQ5: Need extract sector-specific points | AR5: TRUE | AS5: TRUE | AT5: FALSE | AU5: low | AV5: =IF(AND(Q5<>"",Q5<=TODAY()),"Due","") | AW5: commodity
A6: EBL-0005 | B6: Argos Mid-Market Index Q1 2026 | C6: ka_benchmark_Argos_Midmarket_Index_Europe_2026Q1_v1 | D6: ka_benchmark | E6: Core Market | F6: Argos Wityu | G6: external | H6: pdf | I6: Cross-Sector | J6: Europe | K6: Founder-led; Family-owned; Independent SME | L6: Valuation; Private Equity | M6: 46113 | N6: 46128 | O6: 46128 | P6: quarterly | Q6: 46219 | R6: recent | S6: medium | T6: high | U6: multi_source | V6: 5 | W6: 5 | X6: 5 | Y6: =V6+W6+X6 -> 15 | Z6: new | AA6: high | AB6: converted | AC6: Knowledge Card; Thesis | AD6: TRUE | AE6: high | AF6: public | AG6: Editor | AK6: https://argos.wityu.fund/ | AL6: linked | AM6: European mid-market multiple tracker. | AN6: One of the strongest references for private mid-market pricing. | AO6: Valuation benchmark for founder conversations. | AP6: Highly useful in mandates. | AQ6: Need Q2 slot reservation | AR6: TRUE | AS6: TRUE | AT6: FALSE | AU6: low | AV6: =IF(AND(Q6<>"",Q6<=TODAY()),"Due","") | AW6: contextual
A7: EBL-0006 | B7: Argos Mid-Market Index Q4 2025 | C7: ka_benchmark_Argos_Midmarket_Index_Europe_2025Q4_v1 | D7: ka_benchmark | E7: Core Market | F7: Argos Wityu | G7: external | H7: pdf | I7: Cross-Sector | J7: Europe | K7: Founder-led; Family-owned | L7: Valuation; Private Equity | M7: 46032 | N7: 46128 | O7: 46128 | P7: quarterly | Q7: 46219 | R7: recent | S7: medium | T7: high | U7: multi_source | V7: 4 | W7: 4 | X7: 5 | Y7: =V7+W7+X7 -> 13 | Z7: known_pattern | AA7: medium | AB7: validated | AC7: Knowledge Card | AD7: FALSE | AE7: medium | AF7: public | AG7: Editor | AK7: https://argos.wityu.fund/ | AL7: linked | AM7: Prior quarter Argos reference. | AN7: Useful for quarter-over-quarter multiple trend. | AO7: Can feed chart updates. | AP7: Useful for discussion prep. | AQ7: Need compare with Q1 | AR7: TRUE | AS7: FALSE | AT7: FALSE | AU7: low | AV7: =IF(AND(Q7<>"",Q7<=TODAY()),"Due","") | AW7: contextual
A8: EBL-0007 | B8: Clearwater Mid-Market Monitor H1 2026 | C8: ka_benchmark_Clearwater_Midmarket_Monitor_Europe_2026H1_v1 | D8: ka_benchmark | E8: Core Market | F8: Clearwater International | G8: external | H8: pdf | I8: Cross-Sector | J8: Europe; Benelux | K8: Founder-led; Family-owned; Independent SME | L8: Private Equity; Sector Consolidation | M8: 46096 | N8: 46128 | O8: 46128 | P8: quarterly | Q8: 46219 | R8: recent | S8: medium | T8: medium | U8: single_source | V8: 4 | W8: 4 | X8: 4 | Y8: =V8+W8+X8 -> 12 | Z8: new | AA8: high | AB8: triage | AC8: Knowledge Card | AD8: FALSE | AE8: medium | AF8: public | AG8: Analyst | AK8: https://www.clearwaterinternational.com/ | AL8: linked | AM8: Mid-market activity monitor with sector views. | AN8: Good practical monitor for Benelux-facing conversations. | AO8: Can support sector heatmaps and local momentum notes. | AP8: Useful in outreach preparation. | AQ8: Need validate with another source | AR8: TRUE | AS8: TRUE | AT8: FALSE | AU8: medium | AV8: =IF(AND(Q8<>"",Q8<=TODAY()),"Due","") | AW8: contextual
A9: EBL-0008 | B9: Clearwater Mid-Market Monitor Q4 2025 | C9: ka_benchmark_Clearwater_Midmarket_Monitor_Europe_2025Q4_v1 | D9: ka_benchmark | E9: Core Market | F9: Clearwater International | G9: external | H9: pdf | I9: Cross-Sector | J9: Europe; Benelux | K9: Founder-led; Family-owned | L9: Private Equity; Sector Consolidation | M9: 46006 | N9: 46128 | P9: quarterly | Q9: 46219 | R9: recent | S9: medium | T9: medium | U9: single_source | V9: 3 | W9: 3 | X9: 4 | Y9: =V9+W9+X9 -> 10 | Z9: known_pattern | AA9: medium | AB9: backlog | AC9: Knowledge Card | AD9: FALSE | AE9: medium | AF9: public | AG9: Analyst | AK9: https://www.clearwaterinternational.com/ | AL9: linked | AM9: Prior period mid-market monitor. | AN9: Historical compare for trend pieces. | AO9: Useful for quarter comparison. | AP9: Moderate commercial value. | AQ9: Needs summary extraction | AR9: TRUE | AS9: FALSE | AT9: FALSE | AU9: medium | AV9: =IF(AND(Q9<>"",Q9<=TODAY()),"Due","") | AW9: contextual
A10: EBL-0009 | B10: Vlerick M&A Monitor Belux | C10: ka_benchmark_Vlerick_MA_Monitor_Belux_2025_v1 | D10: ka_benchmark | E10: Core Market | F10: Vlerick | G10: external | H10: pdf | I10: Cross-Sector | J10: Belgium; Benelux | K10: Founder-led; Family-owned; Independent SME | L10: Succession; Private Equity; Macro Context | M10: 45962 | N10: 46128 | O10: 46128 | P10: annual | Q10: 46493 | R10: recent | S10: medium | T10: high | U10: multi_source | V10: 5 | W10: 5 | X10: 4 | Y10: =V10+W10+X10 -> 14 | Z10: contextual | AA10: high | AB10: converted | AC10: Knowledge Card; Thesis | AD10: TRUE | AE10: high | AF10: public | AG10: Editor | AK10: https://www.vlerick.com/ | AL10: linked | AM10: Belux-specific M&A market monitor. | AN10: Local credibility layer for conversations in Belgium. | AO10: Can anchor local market articles and founder pieces. | AP10: Highly useful commercially in Belux. | AQ10: Check for newest edition | AR10: TRUE | AS10: TRUE | AT10: FALSE | AU10: low | AV10: =IF(AND(Q10<>"",Q10<=TODAY()),"Due","") | AW10: contextual
A11: EBL-0010 | B11: Invest Europe Annual Activity Report | C11: ka_benchmark_InvestEurope_Activity_Europe_2025_v1 | D11: ka_benchmark | E11: Core Market | F11: Invest Europe | G11: external | H11: pdf | I11: Cross-Sector | J11: Europe | K11: PE-backed; Corporate Buyer | L11: Private Equity; Macro Context | M11: 45823 | N11: 46128 | O11: 46128 | P11: annual | Q11: 46493 | R11: recent | S11: medium | T11: high | U11: multi_source | V11: 4 | W11: 4 | X11: 4 | Y11: =V11+W11+X11 -> 12 | Z11: contextual | AA11: medium | AB11: validated | AC11: Knowledge Card | AD11: FALSE | AE11: medium | AF11: restricted | AG11: Analyst | AK11: https://www.investeurope.eu/ | AL11: linked | AM11: Annual European PE activity data. | AN11: Useful for Europe-wide context and exits. | AO11: Supports broad market sizing and cycle articles. | AP11: Commercially relevant in investor discussions. | AQ11: Need key charts extraction | AR11: TRUE | AS11: TRUE | AT11: FALSE | AU11: low | AV11: =IF(AND(Q11<>"",Q11<=TODAY()),"Due","") | AW11: contextual
A12: EBL-0011 | B12: McKinsey Private Markets Annual Review | C12: ka_benchmark_McKinsey_Private_Markets_Global_2025_v1 | D12: ka_benchmark | E12: Core Market | F12: McKinsey | G12: external | H12: pdf | I12: Cross-Sector | J12: Global; Europe | K12: PE-backed; Corporate Buyer | L12: Private Equity; Macro Context | M12: 45992 | N12: 46128 | O12: 46128 | P12: annual | Q12: 46493 | R12: recent | S12: medium | T12: high | U12: multi_source | V12: 4 | W12: 3 | X12: 4 | Y12: =V12+W12+X12 -> 11 | Z12: contextual | AA12: medium | AB12: validated | AC12: Knowledge Card | AD12: FALSE | AE12: medium | AF12: public | AG12: Editor | AK12: https://www.mckinsey.com/ | AL12: linked | AM12: Broad review of private markets dynamics. | AN12: Useful as a high-level PE framing source. | AO12: Can support thought leadership and investor behavior context. | AP12: Moderate direct mandate value. | AQ12: Need distill non-obvious angles | AR12: TRUE | AS12: TRUE | AT12: FALSE | AU12: low | AV12: =IF(AND(Q12<>"",Q12<=TODAY()),"Due","") | AW12: commodity
A13: EBL-0012 | B13: BDO Private Equity Sentiment Survey | C13: ka_benchmark_BDO_PE_Sentiment_Global_2025_v1 | D13: ka_benchmark | E13: Core Market | F13: BDO | G13: external | H13: pdf | I13: Cross-Sector | J13: Global; Europe | K13: PE-backed; Corporate Buyer | L13: Buyer Psychology; Private Equity | M13: 45901 | N13: 46128 | O13: 46128 | P13: annual | Q13: 46493 | R13: recent | S13: medium | T13: medium | U13: single_source | V13: 3 | W13: 4 | X13: 3 | Y13: =V13+W13+X13 -> 10 | Z13: contextual | AA13: medium | AB13: triage | AC13: Knowledge Card | AD13: FALSE | AE13: medium | AF13: public | AG13: Analyst | AK13: https://www.bdo.global/ | AL13: linked | AM13: PE sentiment survey with buyer expectations. | AN13: Good soft layer for buyer mood and expectations. | AO13: Useful in buyer psychology narratives. | AP13: Helpful but not definitive commercially. | AQ13: Need cross-check with other sentiment data | AR13: TRUE | AS13: FALSE | AT13: FALSE | AU13: medium | AV13: =IF(AND(Q13<>"",Q13<=TODAY()),"Due","") | AW13: contextual
A14: EBL-0013 | B14: Damodaran Latest Dataset | C14: ka_benchmark_Damodaran_Valuation_Global_2026_v1 | D14: ka_benchmark | E14: Valuation & Capital | F14: V4G Internal | G14: mixed | H14: dataset | I14: Cross-Sector | J14: Global | K14: Corporate Buyer; PE-backed | L14: Valuation; Capital Structure | M14: 46027 | N14: 46128 | O14: 46128 | P14: annual | Q14: 46493 | R14: reference | S14: timeless | T14: high | U14: multi_source | V14: 5 | W14: 5 | X14: 5 | Y14: =V14+W14+X14 -> 15 | Z14: contextual | AA14: high | AB14: converted | AC14: Internal Standard; Knowledge Card | AD14: TRUE | AE14: internal_only | AF14: internal | AG14: Analyst | AK14: https://pages.stern.nyu.edu/~adamodar/ | AL14: linked | AM14: Annual valuation reference set for betas, risk premiums and market assumptions. | AN14: Core technical backbone for valuation discipline. | AO14: Can feed internal standards and external framing carefully. | AP14: Very high commercial value. | AQ14: Need house assumptions overlay | AR14: TRUE | AS14: TRUE | AT14: TRUE | AU14: low | AV14: =IF(AND(Q14<>"",Q14<=TODAY()),"Due","") | AW14: contextual
A15: EBL-0014 | B15: Damodaran Prior-Year Dataset | C15: ka_benchmark_Damodaran_Valuation_Global_2025_v1 | D15: ka_benchmark | E15: Valuation & Capital | F15: V4G Internal | G15: mixed | H15: dataset | I15: Cross-Sector | J15: Global | K15: Corporate Buyer; PE-backed | L15: Valuation; Capital Structure | M15: 45662 | N15: 46128 | O15: 46128 | P15: annual | Q15: 46493 | R15: reference | S15: timeless | T15: high | U15: multi_source | V15: 4 | W15: 4 | X15: 5 | Y15: =V15+W15+X15 -> 13 | Z15: known_pattern | AA15: medium | AB15: validated | AC15: Internal Standard | AD15: FALSE | AE15: internal_only | AF15: internal | AG15: Analyst | AK15: https://pages.stern.nyu.edu/~adamodar/ | AL15: linked | AM15: Prior year dataset for trend comparison. | AN15: Useful for change-over-time valuation assumptions. | AO15: Internal reference only. | AP15: Commercial support use. | AQ15: Keep for longitudinal checks | AR15: TRUE | AS15: TRUE | AT15: TRUE | AU15: low | AV15: =IF(AND(Q15<>"",Q15<=TODAY()),"Due","") | AW15: contextual
A16: EBL-0015 | B16: Lincoln International Private Market Index Q1 2026 | C16: ka_benchmark_Lincoln_Private_Market_Index_Global_2026Q1_v1 | D16: ka_benchmark | E16: Valuation & Capital | F16: Lincoln International | G16: external | H16: pdf | I16: Cross-Sector | J16: Global; Europe | K16: PE-backed; Corporate Buyer | L16: Valuation; Private Equity | M16: 46113 | N16: 46128 | O16: 46128 | P16: quarterly | Q16: 46219 | R16: recent | S16: medium | T16: high | U16: multi_source | V16: 5 | W16: 5 | X16: 5 | Y16: =V16+W16+X16 -> 15 | Z16: new | AA16: high | AB16: converted | AC16: Knowledge Card; Thesis | AD16: TRUE | AE16: high | AF16: public | AG16: Editor | AK16: https://www.lincolninternational.com/ | AL16: linked | AM16: Quarterly private market pricing and performance reference. | AN16: Strong source for practical private market pricing context. | AO16: Excellent for valuation conversations and content. | AP16: High commercial relevance. | AQ16: Track next quarter release | AR16: TRUE | AS16: TRUE | AT16: FALSE | AU16: low | AV16: =IF(AND(Q16<>"",Q16<=TODAY()),"Due","") | AW16: contextual
A17: EBL-0016 | B17: Lincoln International Private Market Index Q4 2025 | C17: ka_benchmark_Lincoln_Private_Market_Index_Global_2025Q4_v1 | D17: ka_benchmark | E17: Valuation & Capital | F17: Lincoln International | G17: external | H17: pdf | I17: Cross-Sector | J17: Global; Europe | K17: PE-backed; Corporate Buyer | L17: Valuation; Private Equity | M17: 46023 | N17: 46128 | O17: 46128 | P17: quarterly | Q17: 46219 | R17: recent | S17: medium | T17: high | U17: multi_source | V17: 4 | W17: 4 | X17: 5 | Y17: =V17+W17+X17 -> 13 | Z17: known_pattern | AA17: medium | AB17: validated | AC17: Knowledge Card | AD17: FALSE | AE17: medium | AF17: public | AG17: Editor | AK17: https://www.lincolninternational.com/ | AL17: linked | AM17: Prior-quarter private market index. | AN17: Useful for q/q trend narrative. | AO17: Supports valuation charts. | AP17: Useful commercially. | AQ17: Need compare to Q1 | AR17: TRUE | AS17: FALSE | AT17: FALSE | AU17: low | AV17: =IF(AND(Q17<>"",Q17<=TODAY()),"Due","") | AW17: contextual
A18: EBL-0017 | B18: Debt & Leverage Trends (ECB / Bank Source) | C18: ka_benchmark_ECB_Debt_Leverage_Europe_2026_v1 | D18: ka_benchmark | E18: Valuation & Capital | F18: ECB | G18: external | H18: pdf | I18: Cross-Sector | J18: Europe | K18: PE-backed; Corporate Buyer | L18: Capital Structure; Macro Context | M18: 46068 | N18: 46128 | O18: 46128 | P18: monthly | Q18: 46158 | R18: recent | S18: medium | T18: high | U18: multi_source | V18: 4 | W18: 5 | X18: 4 | Y18: =V18+W18+X18 -> 13 | Z18: contextual | AA18: high | AB18: triage | AC18: Knowledge Card; Internal Standard | AD18: FALSE | AE18: medium | AF18: public | AG18: Analyst | AK18: https://www.ecb.europa.eu/ | AL18: linked | AM18: Debt and rate environment context for leverage availability. | AN18: Important for capital structure and execution realism. | AO18: Can support 'certainty matters' pieces. | AP18: Very useful commercially. | AQ18: Need simple summary for partners | AR18: TRUE | AS18: TRUE | AT18: FALSE | AU18: low | AV18: =IF(AND(Q18<>"",Q18<=TODAY()),"Due","") | AW18: contextual
A19: EBL-0018 | B19: Vendor Loan Benchmark — Internal v1 | C19: ka_internal_standard_V4G_Vendor_Loan_Benchmark_BE_2026_v1 | D19: ka_internal_standard | E19: Valuation & Capital | F19: V4G Internal | G19: internal | H19: memo | I19: Cross-Sector | J19: Belgium; Benelux | K19: Founder-led; Family-owned; Independent SME | L19: Vendor Loan; Negotiation; Capital Structure | M19: 46128 | N19: 46128 | O19: 46128 | P19: quarterly | Q19: 46219 | R19: live | S19: high | T19: medium | U19: internal_only | V19: 5 | W19: 5 | X19: 5 | Y19: =V19+W19+X19 -> 15 | Z19: new | AA19: high | AB19: converted | AC19: Internal Standard; Knowledge Card | AD19: FALSE | AE19: internal_only | AF19: internal | AG19: Partner | AL19: attached | AM19: Internal benchmark ranges and usage patterns for vendor loans. | AN19: Core house IP for structuring conversations. | AO19: Can evolve into strong internal standards and selected editorial snippets. | AP19: Very high mandate value. | AQ19: Need collect more deal examples | AR19: TRUE | AS19: TRUE | AT19: TRUE | AU19: medium | AV19: =IF(AND(Q19<>"",Q19<=TODAY()),"Due","") | AW19: proprietary
A20: EBL-0019 | B20: Earn-Out Structures — Internal v1 | C20: ka_internal_standard_V4G_Earnout_Structures_BE_2026_v1 | D20: ka_internal_standard | E20: Valuation & Capital | F20: V4G Internal | G20: internal | H20: memo | I20: Cross-Sector | J20: Belgium; Benelux | K20: Founder-led; Family-owned; PE-backed | L20: Earn-Out; Negotiation; Deal Execution | M20: 46128 | N20: 46128 | O20: 46128 | P20: quarterly | Q20: 46219 | R20: live | S20: high | T20: medium | U20: internal_only | V20: 5 | W20: 5 | X20: 5 | Y20: =V20+W20+X20 -> 15 | Z20: new | AA20: high | AB20: triage | AC20: Internal Standard; Knowledge Card | AD20: FALSE | AE20: internal_only | AF20: internal | AG20: Partner | AL20: attached | AM20: Internal patterns and market standards for earn-outs. | AN20: High-value structuring intelligence. | AO20: Potential strong thought leadership source when abstracted. | AP20: Very strong commercial relevance. | AQ20: Need examples by sector | AR20: TRUE | AS20: TRUE | AT20: TRUE | AU20: medium | AV20: =IF(AND(Q20<>"",Q20<=TODAY()),"Due","") | AW20: proprietary
A21: EBL-0020 | B21: Rollover Benchmarks — Internal v1 | C21: ka_internal_standard_V4G_Rollover_Benchmarks_Benelux_2026_v1 | D21: ka_internal_standard | E21: Valuation & Capital | F21: V4G Internal | G21: internal | H21: memo | I21: Cross-Sector | J21: Benelux | K21: Founder-led; Family-owned; PE-backed | L21: Rollover; Negotiation; Capital Structure | M21: 46128 | N21: 46128 | O21: 46128 | P21: quarterly | Q21: 46219 | R21: live | S21: high | T21: medium | U21: internal_only | V21: 5 | W21: 5 | X21: 4 | Y21: =V21+W21+X21 -> 14 | Z21: new | AA21: high | AB21: triage | AC21: Internal Standard | AD21: FALSE | AE21: internal_only | AF21: internal | AG21: Partner | AL21: attached | AM21: Internal memo on rollover ranges and mechanics. | AN21: Key for equity rollover negotiation context. | AO21: Can sharpen partner conversations. | AP21: High commercial utility. | AQ21: Need standard examples | AR21: TRUE | AS21: TRUE | AT21: TRUE | AU21: medium | AV21: =IF(AND(Q21<>"",Q21<=TODAY()),"Due","") | AW21: proprietary
A22: EBL-0021 | B22: Working Capital Adjustment Patterns — Internal v1 | C22: ka_pattern_V4G_Working_Capital_Adjustment_Benelux_2026_v1 | D22: ka_pattern | E22: Valuation & Capital | F22: V4G Internal | G22: internal | H22: memo | I22: Cross-Sector | J22: Benelux | K22: Founder-led; Family-owned; PE-backed | L22: Working Capital; Deal Execution; Failure Analysis | M22: 46128 | N22: 46128 | O22: 46128 | P22: monthly | Q22: 46158 | R22: live | S22: high | T22: medium | U22: internal_only | V22: 5 | W22: 5 | X22: 5 | Y22: =V22+W22+X22 -> 15 | Z22: new | AA22: high | AB22: triage | AC22: Pattern; Failure Pattern; Internal Standard | AD22: FALSE | AE22: internal_only | AF22: internal | AG22: Editor | AL22: attached | AM22: Internal pattern memo on common working capital adjustment frictions. | AN22: Potentially one of the strongest process alpha assets. | AO22: Can support articles on hidden deal killers. | AP22: Extremely useful commercially. | AQ22: Need collect failed-case examples | AR22: TRUE | AS22: TRUE | AT22: TRUE | AU22: medium | AV22: =IF(AND(Q22<>"",Q22<=TODAY()),"Due","") | AW22: proprietary
A23: EBL-0022 | B23: IESE Search Fund Primer | C23: ka_framework_IESE_Search_Fund_Primer_Global_2025_v1 | D23: ka_framework | E23: Playbooks | F23: IESE | G23: external | H23: pdf | I23: Cross-Sector | J23: Global; Europe | K23: Search Fund; Independent SME | L23: Search Fund; Deal Execution | M23: 45778 | N23: 46128 | O23: 46128 | P23: annual | Q23: 46493 | R23: reference | S23: timeless | T23: high | U23: multi_source | V23: 4 | W23: 4 | X23: 5 | Y23: =V23+W23+X23 -> 13 | Z23: contextual | AA23: medium | AB23: validated | AC23: Knowledge Card; Thesis | AD23: TRUE | AE23: medium | AF23: public | AG23: Editor | AK23: https://www.iese.edu/ | AL23: linked | AM23: Canonical search fund primer. | AN23: Strong framework source for entrepreneurial buyouts. | AO23: Good for search content and buyer mapping. | AP23: Commercially useful in search discussions. | AQ23: Check newest edition | AR23: TRUE | AS23: TRUE | AT23: TRUE | AU23: low | AV23: =IF(AND(Q23<>"",Q23<=TODAY()),"Due","") | AW23: contextual
A24: EBL-0023 | B24: Harvard Business School Search Fund Study | C24: ka_framework_HBS_Search_Fund_Study_Global_2024_v1 | D24: ka_framework | E24: Playbooks | F24: Harvard Business School | G24: external | H24: pdf | I24: Cross-Sector | J24: Global | K24: Search Fund; Independent SME | L24: Search Fund; Private Equity | M24: 45536 | N24: 46128 | O24: 46128 | P24: annual | Q24: 46493 | R24: reference | S24: timeless | T24: high | U24: multi_source | V24: 4 | W24: 4 | X24: 5 | Y24: =V24+W24+X24 -> 13 | Z24: known_pattern | AA24: medium | AB24: validated | AC24: Knowledge Card | AD24: FALSE | AE24: medium | AF24: public | AG24: Analyst | AK24: https://www.hbs.edu/ | AL24: linked | AM24: Search fund outcomes and model study. | AN24: Useful for longitudinal returns and fit discussion. | AO24: Supports search fund education and content. | AP24: Useful in search conversations. | AQ24: Need pair with IESE primer | AR24: TRUE | AS24: TRUE | AT24: TRUE | AU24: low | AV24: =IF(AND(Q24<>"",Q24<=TODAY()),"Due","") | AW24: contextual
A25: EBL-0024 | B25: Transeo MBO/EBO Monitor | C25: ka_framework_Transeo_MBO_EBO_Europe_2025_v1 | D25: ka_framework | E25: Playbooks | F25: Transeo | G25: external | H25: pdf | I25: Cross-Sector | J25: Europe | K25: Founder-led; Family-owned; Search Fund | L25: Succession; Search Fund; Deal Execution | M25: 45931 | N25: 46128 | O25: 46128 | P25: annual | Q25: 46493 | R25: recent | S25: medium | T25: medium | U25: single_source | V25: 4 | W25: 4 | X25: 4 | Y25: =V25+W25+X25 -> 12 | Z25: contextual | AA25: medium | AB25: triage | AC25: Knowledge Card; Thesis | AD25: FALSE | AE25: medium | AF25: public | AG25: Analyst | AK25: https://transeo-association.eu/ | AL25: linked | AM25: European MBO/EBO monitor. | AN25: Useful for management and entrepreneurial buyout routes. | AO25: Good for succession alternatives narratives. | AP25: Commercially useful in owner transition conversations. | AQ25: Need validate with local cases | AR25: TRUE | AS25: TRUE | AT25: FALSE | AU25: medium | AV25: =IF(AND(Q25<>"",Q25<=TODAY()),"Due","") | AW25: contextual
A26: EBL-0025 | B26: Deal Anatomy Template — Internal | C26: ka_internal_standard_V4G_Deal_Anatomy_Template_Global_2026_v1 | D26: ka_internal_standard | E26: Playbooks | F26: V4G Internal | G26: internal | H26: doc | I26: Cross-Sector | J26: Benelux | K26: Cross-sector | L26: Deal Execution; Negotiation | M26: 46128 | N26: 46128 | O26: 46128 | P26: quarterly | Q26: 46219 | R26: live | S26: high | T26: medium | U26: internal_only | V26: 5 | W26: 5 | X26: 5 | Y26: =V26+W26+X26 -> 15 | Z26: new | AA26: high | AB26: triage | AC26: Internal Standard | AD26: FALSE | AE26: internal_only | AF26: internal | AG26: Editor | AL26: attached | AM26: Template to capture how a deal actually unfolded. | AN26: Critical for turning deal experience into reusable IP. | AO26: Feeds patterns, failure library and training. | AP26: High internal commercial leverage. | AQ26: Need standard fields locked | AR26: TRUE | AS26: TRUE | AT26: TRUE | AU26: medium | AV26: =IF(AND(Q26<>"",Q26<=TODAY()),"Due","") | AW26: proprietary
A27: EBL-0026 | B27: Deal Timeline Template — Internal | C27: ka_internal_standard_V4G_Deal_Timeline_Template_Global_2026_v1 | D27: ka_internal_standard | E27: Playbooks | F27: V4G Internal | G27: internal | H27: doc | I27: Cross-Sector | J27: Benelux | K27: Cross-sector | L27: Deal Execution; Pattern Detection | M27: 46128 | N27: 46128 | O27: 46128 | P27: quarterly | Q27: 46219 | R27: live | S27: high | T27: medium | U27: internal_only | V27: 4 | W27: 5 | X27: 5 | Y27: =V27+W27+X27 -> 14 | Z27: new | AA27: high | AB27: triage | AC27: Internal Standard | AD27: FALSE | AE27: internal_only | AF27: internal | AG27: Editor | AL27: attached | AM27: Template to capture actual process timing. | AN27: Essential to build time-to-close intelligence. | AO27: Supports process benchmarking and founder expectation setting. | AP27: Very useful commercially. | AQ27: Need stage definitions | AR27: TRUE | AS27: TRUE | AT27: TRUE | AU27: medium | AV27: =IF(AND(Q27<>"",Q27<=TODAY()),"Due","") | AW27: proprietary
A28: EBL-0027 | B28: DD Friction Checklist — Internal | C28: ka_internal_standard_V4G_DD_Friction_Checklist_Global_2026_v1 | D28: ka_internal_standard | E28: Playbooks | F28: V4G Internal | G28: internal | H28: doc | I28: Cross-Sector | J28: Benelux | K28: Cross-sector | L28: Due Diligence; Failure Analysis | M28: 46128 | N28: 46128 | O28: 46128 | P28: monthly | Q28: 46158 | R28: live | S28: high | T28: medium | U28: internal_only | V28: 5 | W28: 5 | X28: 5 | Y28: =V28+W28+X28 -> 15 | Z28: new | AA28: high | AB28: triage | AC28: Internal Standard; Failure Pattern | AD28: FALSE | AE28: internal_only | AF28: internal | AG28: Partner | AL28: attached | AM28: Checklist of due diligence frictions to capture systematically. | AN28: Strong candidate for process alpha and failure prevention. | AO28: Can become internal diagnostic and later external thought leadership. | AP28: High commercial value. | AQ28: Need example frictions | AR28: TRUE | AS28: TRUE | AT28: TRUE | AU28: medium | AV28: =IF(AND(Q28<>"",Q28<=TODAY()),"Due","") | AW28: proprietary
A29: EBL-0028 | B29: Hampleton Software M&A Report | C29: ka_market_map_Hampleton_Software_Europe_2026_v1 | D29: ka_market_map | E29: Sectors | F29: Clearwater International | G29: external | H29: pdf | I29: Software | J29: Europe | K29: PE-backed; Corporate Buyer; Add-on Target | L29: Sector Consolidation; Valuation | M29: 46054 | N29: 46128 | O29: 46128 | P29: quarterly | Q29: 46219 | R29: recent | S29: medium | T29: medium | U29: single_source | V29: 4 | W29: 4 | X29: 4 | Y29: =V29+W29+X29 -> 12 | Z29: new | AA29: medium | AB29: triage | AC29: Knowledge Card; Thesis | AD29: FALSE | AE29: medium | AF29: public | AG29: Analyst | AK29: https://www.clearwaterinternational.com/ | AL29: linked | AM29: Software M&A report placeholder for sector heatmap. | AN29: Useful to build software market map and buyer logic. | AO29: Feeds sector page and thematic content. | AP29: Useful for software mandates. | AQ29: Confirm preferred source | AR29: TRUE | AS29: TRUE | AT29: FALSE | AU29: medium | AV29: =IF(AND(Q29<>"",Q29<=TODAY()),"Due","") | AW29: contextual
A30: EBL-0029 | B30: DC Advisory Healthcare Review | C30: ka_market_map_DCAdvisory_Healthcare_Europe_2026_v1 | D30: ka_market_map | E30: Sectors | F30: DC Advisory | G30: external | H30: pdf | I30: Healthcare | J30: Europe | K30: Founder-led; PE-backed; Corporate Buyer | L30: Sector Consolidation; Regulation | M30: 46073 | N30: 46128 | O30: 46128 | P30: quarterly | Q30: 46219 | R30: recent | S30: medium | T30: medium | U30: single_source | V30: 4 | W30: 4 | X30: 4 | Y30: =V30+W30+X30 -> 12 | Z30: new | AA30: medium | AB30: triage | AC30: Knowledge Card; Thesis | AD30: FALSE | AE30: medium | AF30: public | AG30: Analyst | AK30: https://www.dcaadvisory.com/ | AL30: linked | AM30: Healthcare sector review and M&A context. | AN30: Important for healthcare regulation and consolidation angles. | AO30: Can support thesis on compliance-driven activity. | AP30: Useful in healthcare dialogues. | AQ30: Need extract Benelux angle | AR30: TRUE | AS30: TRUE | AT30: FALSE | AU30: medium | AV30: =IF(AND(Q30<>"",Q30<=TODAY()),"Due","") | AW30: contextual
A31: EBL-0030 | B31: Alantra Industrials Overview | C31: ka_market_map_Alantra_Industrials_Europe_2026_v1 | D31: ka_market_map | E31: Sectors | F31: Alantra | G31: external | H31: pdf | I31: Industrials | J31: Europe | K31: Founder-led; Family-owned; Corporate Buyer | L31: Sector Consolidation; Succession | M31: 46047 | N31: 46128 | O31: 46128 | P31: quarterly | Q31: 46219 | R31: recent | S31: medium | T31: medium | U31: single_source | V31: 4 | W31: 5 | X31: 4 | Y31: =V31+W31+X31 -> 13 | Z31: new | AA31: medium | AB31: triage | AC31: Knowledge Card | AD31: FALSE | AE31: medium | AF31: public | AG31: Analyst | AK31: https://www.alantra.com/ | AL31: linked | AM31: Industrials sector overview for M&A context. | AN31: Relevant for family-owned industrial transition cases. | AO31: Supports succession and consolidation angles. | AP31: High commercial relevance in industrial mandates. | AQ31: Need map sub-sectors | AR31: TRUE | AS31: TRUE | AT31: FALSE | AU31: medium | AV31: =IF(AND(Q31<>"",Q31<=TODAY()),"Due","") | AW31: contextual
A32: EBL-0031 | B32: Rabobank Food & Agri Outlook | C32: ka_market_map_Rabobank_Food_Agri_Europe_2026_v1 | D32: ka_market_map | E32: Sectors | F32: Rabobank | G32: external | H32: pdf | I32: Food & Agri | J32: Europe | K32: Founder-led; Family-owned; Corporate Buyer | L32: Sector Consolidation; Macro Context | M32: 46063 | N32: 46128 | O32: 46128 | P32: quarterly | Q32: 46219 | R32: recent | S32: medium | T32: high | U32: multi_source | V32: 4 | W32: 5 | X32: 4 | Y32: =V32+W32+X32 -> 13 | Z32: contextual | AA32: high | AB32: validated | AC32: Knowledge Card; Thesis | AD32: TRUE | AE32: medium | AF32: public | AG32: Editor | AK32: https://www.rabobank.com/ | AL32: linked | AM32: Food & agri outlook with sector implications. | AN32: Strong source for sector economics and deal context. | AO32: Can drive food & agri sector page and editorials. | AP32: Commercially useful in agro-related dialogues. | AQ32: Need link local examples | AR32: TRUE | AS32: TRUE | AT32: FALSE | AU32: low | AV32: =IF(AND(Q32<>"",Q32<=TODAY()),"Due","") | AW32: contextual
A33: EBL-0032 | B33: Business Services Sector Report | C33: ka_market_map_V4G_Business_Services_Benelux_2026_v1 | D33: ka_market_map | E33: Sectors | F33: V4G Internal | G33: derived | H33: memo | I33: Business Services | J33: Benelux | K33: Founder-led; PE-backed; Add-on Target | L33: Sector Consolidation; Private Equity | M33: 46128 | N33: 46128 | O33: 46128 | P33: quarterly | Q33: 46219 | R33: live | S33: high | T33: medium | U33: internal_only | V33: 4 | W33: 5 | X33: 4 | Y33: =V33+W33+X33 -> 13 | Z33: new | AA33: high | AB33: triage | AC33: Knowledge Card; Thesis | AD33: FALSE | AE33: internal_only | AF33: internal | AG33: Editor | AL33: attached | AM33: Internal sector memo for business services. | AN33: Good candidate for recurring sector map. | AO33: Supports high-activity PE conversations. | AP33: Strong commercial relevance. | AQ33: Need external source support | AR33: TRUE | AS33: TRUE | AT33: FALSE | AU33: medium | AV33: =IF(AND(Q33<>"",Q33<=TODAY()),"Due","") | AW33: proprietary
A34: EBL-0033 | B34: Transport & Logistics Sector Report | C34: ka_market_map_V4G_Transport_Logistics_Benelux_2026_v1 | D34: ka_market_map | E34: Sectors | F34: V4G Internal | G34: derived | H34: memo | I34: Transport & Logistics | J34: Benelux | K34: Founder-led; Family-owned; Add-on Target | L34: Sector Consolidation; Macro Context | M34: 46128 | N34: 46128 | O34: 46128 | P34: quarterly | Q34: 46219 | R34: live | S34: high | T34: medium | U34: internal_only | V34: 4 | W34: 5 | X34: 4 | Y34: =V34+W34+X34 -> 13 | Z34: new | AA34: high | AB34: triage | AC34: Knowledge Card | AD34: FALSE | AE34: internal_only | AF34: internal | AG34: Editor | AL34: attached | AM34: Internal transport and logistics sector memo. | AN34: Useful for consolidation and regional buyer mapping. | AO34: Can support origination and editorial coverage. | AP34: Strong commercial value. | AQ34: Need add 3 external supports | AR34: TRUE | AS34: TRUE | AT34: FALSE | AU34: medium | AV34: =IF(AND(Q34<>"",Q34<=TODAY()),"Due","") | AW34: proprietary
A35: EBL-0034 | B35: Construction / Infra Sector Report | C35: ka_market_map_V4G_Construction_Infra_Benelux_2026_v1 | D35: ka_market_map | E35: Sectors | F35: V4G Internal | G35: derived | H35: memo | I35: Construction | J35: Benelux | K35: Founder-led; Family-owned; Corporate Buyer | L35: Sector Consolidation; Succession | M35: 46128 | N35: 46128 | O35: 46128 | P35: quarterly | Q35: 46219 | R35: live | S35: high | T35: medium | U35: internal_only | V35: 4 | W35: 5 | X35: 4 | Y35: =V35+W35+X35 -> 13 | Z35: new | AA35: high | AB35: triage | AC35: Knowledge Card | AD35: FALSE | AE35: internal_only | AF35: internal | AG35: Editor | AL35: attached | AM35: Internal construction and infra sector memo. | AN35: Supports fragmentation and succession themes. | AO35: Useful in mandate positioning. | AP35: High commercial utility. | AQ35: Need local market sizing | AR35: TRUE | AS35: TRUE | AT35: FALSE | AU35: medium | AV35: =IF(AND(Q35<>"",Q35<=TODAY()),"Due","") | AW35: proprietary
A36: EBL-0035 | B36: Energy Transition M&A Report | C36: ka_market_map_V4G_Energy_Transition_Europe_2026_v1 | D36: ka_market_map | E36: Sectors | F36: V4G Internal | G36: derived | H36: memo | I36: Energy | J36: Europe | K36: Corporate Buyer; PE-backed | L36: Sector Consolidation; Macro Context; Regulation | M36: 46128 | N36: 46128 | P36: quarterly | Q36: 46219 | R36: live | S36: high | T36: medium | U36: single_source | V36: 3 | W36: 4 | X36: 3 | Y36: =V36+W36+X36 -> 10 | Z36: new | AA36: medium | AB36: backlog | AC36: Knowledge Card | AD36: FALSE | AE36: medium | AF36: internal | AG36: Analyst | AL36: attached | AM36: Energy transition sector report placeholder. | AN36: Potentially useful but less core initially. | AO36: Could support thematic angles when relevant. | AP36: Moderate commercial relevance. | AQ36: Need select external anchor sources | AR36: TRUE | AS36: FALSE | AT36: FALSE | AU36: high | AV36: =IF(AND(Q36<>"",Q36<=TODAY()),"Due","") | AW36: proprietary
A37: EBL-0036 | B37: PE Holding Periods Analysis — Internal | C37: ka_pattern_V4G_PE_Holding_Periods_Europe_2026_v1 | D37: ka_pattern | E37: Investor Models | F37: V4G Internal | G37: derived | H37: memo | I37: Cross-Sector | J37: Europe | K37: PE-backed; Corporate Buyer | L37: Private Equity; Pattern Detection | M37: 46128 | N37: 46128 | O37: 46128 | P37: monthly | Q37: 46158 | R37: live | S37: high | T37: medium | U37: internal_only | V37: 4 | W37: 4 | X37: 5 | Y37: =V37+W37+X37 -> 13 | Z37: new | AA37: medium | AB37: triage | AC37: Pattern; Thesis | AD37: FALSE | AE37: internal_only | AF37: internal | AG37: Editor | AL37: attached | AM37: Internal view on hold periods and implications. | AN37: Useful for exit pressure narratives. | AO37: Can become recurring pattern asset. | AP37: Helpful in investor conversations. | AQ37: Need benchmark support | AR37: TRUE | AS37: TRUE | AT37: FALSE | AU37: medium | AV37: =IF(AND(Q37<>"",Q37<=TODAY()),"Due","") | AW37: proprietary
A38: EBL-0037 | B38: Platform vs Add-On Strategy Doc — Internal | C38: ka_pattern_V4G_Platform_vs_Addon_Europe_2026_v1 | D38: ka_pattern | E38: Investor Models | F38: V4G Internal | G38: internal | H38: memo | I38: Cross-Sector | J38: Europe | K38: PE-backed; Buy-and-Build Platform; Add-on Target | L38: Private Equity; Deal Execution | M38: 46128 | N38: 46128 | O38: 46128 | P38: monthly | Q38: 46158 | R38: live | S38: high | T38: medium | U38: internal_only | V38: 5 | W38: 5 | X38: 5 | Y38: =V38+W38+X38 -> 15 | Z38: new | AA38: high | AB38: converted | AC38: Pattern; Internal Standard | AD38: FALSE | AE38: internal_only | AF38: internal | AG38: Partner | AL38: attached | AM38: Internal strategy note on platform versus add-on behavior. | AN38: Highly useful for buyer mapping and sell-side positioning. | AO38: Can drive repeatable PE explanations. | AP38: Very high commercial value. | AQ38: Need examples by fund type | AR38: TRUE | AS38: TRUE | AT38: FALSE | AU38: medium | AV38: =IF(AND(Q38<>"",Q38<=TODAY()),"Due","") | AW38: proprietary
A39: EBL-0038 | B39: Sponsor Behavior Notes — Internal | C39: ka_pattern_V4G_Sponsor_Behavior_Europe_2026_v1 | D39: ka_pattern | E39: Investor Models | F39: V4G Internal | G39: internal | H39: memo | I39: Cross-Sector | J39: Europe | K39: PE-backed | L39: Buyer Psychology; Private Equity | M39: 46128 | N39: 46128 | O39: 46128 | P39: monthly | Q39: 46158 | R39: live | S39: high | T39: medium | U39: internal_only | V39: 4 | W39: 4 | X39: 5 | Y39: =V39+W39+X39 -> 13 | Z39: new | AA39: medium | AB39: triage | AC39: Pattern | AD39: FALSE | AE39: internal_only | AF39: internal | AG39: Editor | AL39: attached | AM39: Internal notes on sponsor behavior and process style. | AN39: Good input for buyer psychology library. | AO39: Supports preparation and messaging. | AP39: Moderate to high commercial value. | AQ39: Need codify by sponsor archetype | AR39: TRUE | AS39: TRUE | AT39: FALSE | AU39: medium | AV39: =IF(AND(Q39<>"",Q39<=TODAY()),"Due","") | AW39: proprietary
A40: EBL-0039 | B40: Exit Timing Patterns — Internal | C40: ka_pattern_V4G_Exit_Timing_Europe_2026_v1 | D40: ka_pattern | E40: Investor Models | F40: V4G Internal | G40: internal | H40: memo | I40: Cross-Sector | J40: Europe | K40: PE-backed; Corporate Buyer | L40: Private Equity; Macro Context; Pattern Detection | M40: 46128 | N40: 46128 | O40: 46128 | P40: monthly | Q40: 46158 | R40: live | S40: high | T40: medium | U40: internal_only | V40: 4 | W40: 4 | X40: 4 | Y40: =V40+W40+X40 -> 12 | Z40: new | AA40: medium | AB40: triage | AC40: Pattern; Thesis | AD40: FALSE | AE40: internal_only | AF40: internal | AG40: Editor | AL40: attached | AM40: Internal memo on exit timing patterns and triggers. | AN40: Useful for reading market windows and sponsor behavior. | AO40: Can support strategic timing theses. | AP40: Commercially relevant for preparation conversations. | AQ40: Need integrate macro layer | AR40: TRUE | AS40: TRUE | AT40: FALSE | AU40: medium | AV40: =IF(AND(Q40<>"",Q40<=TODAY()),"Due","") | AW40: proprietary
A41: EBL-0040 | B41: IMF Economic Outlook | C41: ka_library_source_IMF_Economic_Outlook_Global_2026_v1 | D41: ka_library_source | E41: Macro | F41: IMF | G41: external | H41: pdf | I41: Cross-Sector | J41: Global; Europe | K41: Cross-sector | L41: Macro Context | M41: 46113 | N41: 46128 | O41: 46128 | P41: annual | Q41: 46493 | R41: recent | S41: medium | T41: high | U41: multi_source | V41: 3 | W41: 3 | X41: 4 | Y41: =V41+W41+X41 -> 10 | Z41: contextual | AA41: medium | AB41: validated | AC41: Thesis | AD41: FALSE | AE41: low | AF41: public | AG41: Analyst | AK41: https://www.imf.org/ | AL41: linked | AM41: Macro outlook source for broad economic framing. | AN41: Useful for narrative backdrop, not core differentiation. | AO41: Can support top-down timing pieces. | AP41: Lower direct commercial value. | AQ41: Need concise extracts only | AR41: TRUE | AS41: FALSE | AT41: FALSE | AU41: low | AV41: =IF(AND(Q41<>"",Q41<=TODAY()),"Due","") | AW41: commodity
A42: EBL-0041 | B42: OECD Economic Outlook | C42: ka_library_source_OECD_Economic_Outlook_Europe_2026_v1 | D42: ka_library_source | E42: Macro | F42: OECD | G42: external | H42: pdf | I42: Cross-Sector | J42: Europe | K42: Cross-sector | L42: Macro Context | M42: 46101 | N42: 46128 | O42: 46128 | P42: annual | Q42: 46493 | R42: recent | S42: medium | T42: high | U42: multi_source | V42: 3 | W42: 3 | X42: 4 | Y42: =V42+W42+X42 -> 10 | Z42: contextual | AA42: medium | AB42: validated | AC42: Thesis | AD42: FALSE | AE42: low | AF42: public | AG42: Analyst | AK42: https://www.oecd.org/ | AL42: linked | AM42: OECD outlook with Europe emphasis. | AN42: Useful for European economic framing. | AO42: Can support articles on timing and climate. | AP42: Low-to-moderate commercial value. | AQ42: Need selective usage | AR42: TRUE | AS42: FALSE | AT42: FALSE | AU42: low | AV42: =IF(AND(Q42<>"",Q42<=TODAY()),"Due","") | AW42: commodity
A43: EBL-0042 | B43: EY CEO Outlook | C43: ka_library_source_EY_CEO_Outlook_Global_2025_v1 | D43: ka_library_source | E43: Macro | F43: EY | G43: external | H43: pdf | I43: Cross-Sector | J43: Global; Europe | K43: Corporate Buyer | L43: Buyer Psychology; Macro Context | M43: 45931 | N43: 46128 | O43: 46128 | P43: annual | Q43: 46493 | R43: recent | S43: medium | T43: medium | U43: single_source | V43: 3 | W43: 3 | X43: 3 | Y43: =V43+W43+X43 -> 9 | Z43: contextual | AA43: low | AB43: triage | AC43: Thesis | AD43: FALSE | AE43: low | AF43: public | AG43: Analyst | AK43: https://www.ey.com/ | AL43: linked | AM43: CEO outlook survey on strategic intent. | AN43: Potential support for buyer appetite narratives. | AO43: Use selectively in broader pieces. | AP43: Low direct commercial relevance. | AQ43: Need test usefulness | AR43: TRUE | AS43: FALSE | AT43: FALSE | AU43: medium | AV43: =IF(AND(Q43<>"",Q43<=TODAY()),"Due","") | AW43: commodity
A44: EBL-0043 | B44: BCG M&A Perspectives | C44: ka_library_source_BCG_MA_Perspectives_Global_2025_v1 | D44: ka_library_source | E44: Macro | F44: BCG | G44: external | H44: pdf | I44: Cross-Sector | J44: Global | K44: Corporate Buyer; PE-backed | L44: Macro Context; Sector Consolidation | M44: 45976 | N44: 46128 | O44: 46128 | P44: annual | Q44: 46493 | R44: recent | S44: medium | T44: medium | U44: single_source | V44: 3 | W44: 3 | X44: 3 | Y44: =V44+W44+X44 -> 9 | Z44: contextual | AA44: low | AB44: triage | AC44: Thesis | AD44: FALSE | AE44: low | AF44: public | AG44: Analyst | AK44: https://www.bcg.com/ | AL44: linked | AM44: M&A perspectives source for framing and language. | AN44: Useful as secondary support, not core edge. | AO44: Can inspire narrative framing. | AP44: Limited commercial value. | AQ44: Need extract any differentiated points | AR44: TRUE | AS44: FALSE | AT44: FALSE | AU44: medium | AV44: =IF(AND(Q44<>"",Q44<=TODAY()),"Due","") | AW44: commodity
A45: EBL-0044 | B45: Interest Rate Evolution (ECB) | C45: ka_library_source_ECB_Interest_Rates_Europe_2026_v1 | D45: ka_library_source | E45: Macro | F45: ECB | G45: external | H45: dataset | I45: Cross-Sector | J45: Europe | K45: Cross-sector | L45: Macro Context; Capital Structure | M45: 46113 | N45: 46128 | O45: 46128 | P45: monthly | Q45: 46158 | R45: recent | S45: medium | T45: high | U45: multi_source | V45: 4 | W45: 4 | X45: 4 | Y45: =V45+W45+X45 -> 12 | Z45: contextual | AA45: medium | AB45: validated | AC45: Knowledge Card; Thesis | AD45: TRUE | AE45: medium | AF45: public | AG45: Analyst | AK45: https://www.ecb.europa.eu/ | AL45: linked | AM45: Rates dataset to contextualize leverage and deal appetite. | AN45: Useful macro mechanic with real execution relevance. | AO45: Supports debt-cost narratives and buyer caution points. | AP45: Commercially useful in debt-sensitive conversations. | AQ45: Need simple chart layer | AR45: TRUE | AS45: TRUE | AT45: FALSE | AU45: low | AV45: =IF(AND(Q45<>"",Q45<=TODAY()),"Due","") | AW45: contextual
A46: EBL-0045 | B46: Dealflow.news Top 10 Articles Bundle | C46: ka_editorial_angle_Dealflow_Bundle_Benelux_2026_v1 | D46: ka_editorial_angle | E46: Editorial | F46: Dealflow.news | G46: internal | H46: bundle | I46: Cross-Sector | J46: Belgium; Benelux | K46: Cross-sector | L46: Editorial Narrative; Pattern Detection | M46: 46128 | N46: 46128 | O46: 46128 | P46: monthly | Q46: 46158 | R46: live | S46: high | T46: medium | U46: internal_only | V46: 5 | W46: 4 | X46: 5 | Y46: =V46+W46+X46 -> 14 | Z46: new | AA46: high | AB46: triage | AC46: Editorial Angle; Thesis | AD46: FALSE | AE46: internal_only | AF46: internal | AG46: Editor | AK46: https://dealflow.news/ | AL46: linked | AM46: Bundle of strongest existing editorial pieces. | AN46: Key source for recycling house voice and ideas. | AO46: Can be decomposed into patterns, angles and theses. | AP46: High strategic editorial value. | AQ46: Need annotate per article | AR46: TRUE | AS46: TRUE | AT46: FALSE | AU46: medium | AV46: =IF(AND(Q46<>"",Q46<=TODAY()),"Due","") | AW46: proprietary
A47: EBL-0046 | B47: LinkedIn Insights Bundle | C47: ka_signal_digest_LinkedIn_Insights_Benelux_2026_v1 | D47: ka_signal_digest | E47: Editorial | F47: Partner Insight | G47: mixed | H47: bundle | I47: Cross-Sector | J47: Belgium; Benelux | K47: Cross-sector | L47: Editorial Narrative; Signal Detection | M47: 46128 | N47: 46128 | O47: 46128 | P47: weekly | Q47: 46135 | R47: live | S47: high | T47: low | U47: sensitive | V47: 4 | W47: 4 | X47: 4 | Y47: =V47+W47+X47 -> 12 | Z47: new | AA47: high | AB47: triage | AC47: Signal Digest; Editorial Angle | AD47: FALSE | AE47: internal_only | AF47: internal | AG47: Editor | AL47: attached | AM47: Curated bundle of LinkedIn observations and partner signals. | AN47: Good soft-signal layer for topicality and watchlists. | AO47: Can surface early editorial hooks. | AP47: Useful commercially when linked to sectors. | AQ47: Need reliability grading | AR47: TRUE | AS47: TRUE | AT47: FALSE | AU47: high | AV47: =IF(AND(Q47<>"",Q47<=TODAY()),"Due","") | AW47: proprietary
A48: EBL-0047 | B48: Sector Theses Bundle — Internal | C48: ka_thesis_V4G_Sector_Theses_Benelux_2026_v1 | D48: ka_thesis | E48: Editorial | F48: V4G Internal | G48: internal | H48: memo | I48: Cross-Sector | J48: Benelux | K48: Cross-sector | L48: Editorial Narrative; Sector Consolidation | M48: 46128 | N48: 46128 | O48: 46128 | P48: quarterly | Q48: 46219 | R48: live | S48: high | T48: medium | U48: internal_only | V48: 5 | W48: 5 | X48: 5 | Y48: =V48+W48+X48 -> 15 | Z48: new | AA48: high | AB48: triage | AC48: Thesis | AD48: FALSE | AE48: internal_only | AF48: internal | AG48: Editor | AL48: attached | AM48: Bundle of early sector theses for priority verticals. | AN48: Could become the most differentiating editorial layer. | AO48: Directly supports partner positioning and content. | AP48: Very high commercial and editorial value. | AQ48: Need split into individual theses | AR48: TRUE | AS48: TRUE | AT48: FALSE | AU48: medium | AV48: =IF(AND(Q48<>"",Q48<=TODAY()),"Due","") | AW48: proprietary
A49: EBL-0048 | B49: Buyer Mindset Memo — Internal | C49: ka_pattern_V4G_Buyer_Mindset_Benelux_2026_v1 | D49: ka_pattern | E49: Patterns | F49: V4G Internal | G49: internal | H49: memo | I49: Cross-Sector | J49: Benelux | K49: Corporate Buyer; PE-backed | L49: Buyer Psychology; Negotiation | M49: 46128 | N49: 46128 | O49: 46128 | P49: monthly | Q49: 46158 | R49: live | S49: high | T49: medium | U49: internal_only | V49: 5 | W49: 5 | X49: 5 | Y49: =V49+W49+X49 -> 15 | Z49: new | AA49: high | AB49: converted | AC49: Pattern; Thesis | AD49: FALSE | AE49: internal_only | AF49: internal | AG49: Partner | AL49: attached | AM49: Internal memo on buyer conviction and hesitation patterns. | AN49: Strong soft-power asset for process interpretation. | AO49: Can support articles and negotiation preparation. | AP49: Very high commercial use. | AQ49: Need archetypes and examples | AR49: TRUE | AS49: TRUE | AT49: FALSE | AU49: medium | AV49: =IF(AND(Q49<>"",Q49<=TODAY()),"Due","") | AW49: proprietary
A50: EBL-0049 | B50: Founder Hesitation Memo — Internal | C50: ka_pattern_V4G_Founder_Hesitation_BE_2026_v1 | D50: ka_pattern | E50: Patterns | F50: V4G Internal | G50: internal | H50: memo | I50: Cross-Sector | J50: Belgium; Benelux | K50: Founder-led; Family-owned | L50: Founder Psychology; Succession | M50: 46128 | N50: 46128 | O50: 46128 | P50: monthly | Q50: 46158 | R50: live | S50: high | T50: medium | U50: internal_only | V50: 5 | W50: 5 | X50: 5 | Y50: =V50+W50+X50 -> 15 | Z50: new | AA50: high | AB50: converted | AC50: Pattern; Thesis; Editorial Angle | AD50: FALSE | AE50: internal_only | AF50: internal | AG50: Partner | AL50: attached | AM50: Internal founder hesitation pattern memo. | AN50: Likely core proprietary insight library item. | AO50: Very strong for both content and mandate work. | AP50: Extremely high commercial relevance. | AQ50: Need map triggers by phase | AR50: TRUE | AS50: TRUE | AT50: FALSE | AU50: medium | AV50: =IF(AND(Q50<>"",Q50<=TODAY()),"Due","") | AW50: proprietary
A51: EBL-0050 | B51: Negotiation Patterns Memo — Internal | C51: ka_pattern_V4G_Negotiation_Patterns_Benelux_2026_v1 | D51: ka_pattern | E51: Patterns | F51: V4G Internal | G51: internal | H51: memo | I51: Cross-Sector | J51: Benelux | K51: Founder-led; Family-owned; PE-backed | L51: Negotiation; Deal Execution | M51: 46128 | N51: 46128 | O51: 46128 | P51: monthly | Q51: 46158 | R51: live | S51: high | T51: medium | U51: internal_only | V51: 5 | W51: 5 | X51: 5 | Y51: =V51+W51+X51 -> 15 | Z51: new | AA51: high | AB51: triage | AC51: Pattern; Internal Standard | AD51: FALSE | AE51: internal_only | AF51: internal | AG51: Partner | AL51: attached | AM51: Internal memo on recurring negotiation patterns. | AN51: Critical reusable process intelligence. | AO51: Can support playbooks and editorial excerpts. | AP51: Very high commercial utility. | AQ51: Need clause-level taxonomy | AR51: TRUE | AS51: TRUE | AT51: FALSE | AU51: medium | AV51: =IF(AND(Q51<>"",Q51<=TODAY()),"Due","") | AW51: proprietary
A52: EBL-0051 | B52: Deal Failure Case Register — Internal | C52: ka_failure_pattern_V4G_Deal_Failure_Register_Benelux_2026_v1 | D52: ka_failure_pattern | E52: Failure | F52: V4G Internal | G52: internal | H52: sheet | I52: Cross-Sector | J52: Belgium; Benelux | K52: Founder-led; Family-owned; PE-backed | L52: Failure Analysis; Deal Execution; Pattern Detection | M52: 46128 | N52: 46128 | O52: 46128 | P52: monthly | Q52: 46158 | R52: live | S52: high | T52: medium | U52: internal_only | V52: 5 | W52: 5 | X52: 5 | Y52: =V52+W52+X52 -> 15 | Z52: new | AA52: high | AB52: converted | AC52: Failure Pattern; Internal Standard | AD52: FALSE | AE52: internal_only | AF52: internal | AG52: Partner | AL52: attached | AM52: Structured register capturing deals that did NOT close — why, when, and what signals preceded failure. | AN52: Pure alpha. Nobody builds this. Feeds failure prevention and process credibility. | AO52: Hidden deal killers, failure taxonomy, early-warning signals. | AP52: Extremely high — prevents repeated mistakes and builds founder trust. | AQ52: Need minimum 5 case entries to activate | AR52: TRUE | AS52: TRUE | AT52: TRUE | AU52: low | AV52: =IF(AND(Q52<>"",Q52<=TODAY()),"Due","") | AW52: proprietary
A53: EBL-0052 | B53: Failure Trigger Taxonomy — Internal | C53: ka_failure_pattern_V4G_Failure_Triggers_Benelux_2026_v1 | D53: ka_failure_pattern | E53: Failure | F53: V4G Internal | G53: internal | H53: memo | I53: Cross-Sector | J53: Belgium; Benelux | K53: Founder-led; Family-owned; PE-backed | L53: Failure Analysis; Negotiation; Due Diligence | M53: 46128 | N53: 46128 | O53: 46128 | P53: monthly | Q53: 46158 | R53: live | S53: high | T53: medium | U53: internal_only | V53: 5 | W53: 5 | X53: 5 | Y53: =V53+W53+X53 -> 15 | Z53: new | AA53: high | AB53: triage | AC53: Failure Pattern; Internal Standard | AD53: FALSE | AE53: internal_only | AF53: internal | AG53: Editor | AL53: attached | AM53: Taxonomy of failure triggers: pricing mismatch, DD friction, founder cold feet, buyer withdrawal, regulatory block. | AN53: Converts raw failure data into codified intelligence for pattern detection. | AO53: Failure categories, trigger mapping, prevention playbooks. | AP53: High — enables proactive risk management in live processes. | AQ53: Need classify triggers by deal phase | AR53: TRUE | AS53: TRUE | AT53: TRUE | AU53: low | AV53: =IF(AND(Q53<>"",Q53<=TODAY()),"Due","") | AW53: proprietary
A54: EBL-0053 | B54: Phase Failure Analysis — Internal | C54: ka_failure_pattern_V4G_Phase_Failure_Benelux_2026_v1 | D54: ka_failure_pattern | E54: Failure | F54: V4G Internal | G54: internal | H54: memo | I54: Cross-Sector | J54: Belgium; Benelux | K54: Founder-led; Family-owned; PE-backed | L54: Failure Analysis; Deal Execution; Pattern Detection | M54: 46128 | N54: 46128 | O54: 46128 | P54: monthly | Q54: 46158 | R54: live | S54: high | T54: medium | U54: internal_only | V54: 5 | W54: 5 | X54: 5 | Y54: =V54+W54+X54 -> 15 | Z54: new | AA54: high | AB54: triage | AC54: Failure Pattern; Knowledge Card | AD54: FALSE | AE54: internal_only | AF54: internal | AG54: Editor | AL54: attached | AM54: Analysis of WHEN deals fail by process phase: pre-LOI, DD, SPA negotiation, closing conditions. | AN54: Maps failure risk by phase — enables targeted intervention at high-risk moments. | AO54: Phase-specific failure rates, intervention windows, preventive actions. | AP54: Very high — directly feeds process management and founder expectation setting. | AQ54: Need minimum 10 data points per phase | AR54: TRUE | AS54: TRUE | AT54: TRUE | AU54: low | AV54: =IF(AND(Q54<>"",Q54<=TODAY()),"Due","") | AW54: proprietary
A55: EBL-0054 | B55: Time-to-Close: Sector vs Speed — Internal | C55: ka_pattern_V4G_Time_to_Close_Sector_Benelux_2026_v1 | D55: ka_pattern | E55: System | F55: V4G Internal | G55: internal | H55: dataset | I55: Cross-Sector | J55: Belgium; Benelux | K55: Cross-sector | L55: Deal Execution; Pattern Detection; Sector Consolidation | M55: 46128 | N55: 46128 | O55: 46128 | P55: quarterly | Q55: 46219 | R55: live | S55: high | T55: medium | U55: internal_only | V55: 5 | W55: 5 | X55: 5 | Y55: =V55+W55+X55 -> 15 | Z55: new | AA55: high | AB55: triage | AC55: Pattern; Internal Standard | AD55: FALSE | AE55: internal_only | AF55: internal | AG55: Analyst | AL55: attached | AM55: Dataset tracking average time-to-close by sector — reveals which verticals move fast or slow. | AN55: Extreem waardevol voor buy-side positioning en founder expectation management. | AO55: Sector speed rankings, bottleneck identification, process benchmarking. | AP55: Very high — sets realistic timelines in mandates and impresses buyers. | AQ55: Need minimum 15 closed deals to generate reliable averages | AR55: TRUE | AS55: TRUE | AT55: TRUE | AU55: low | AV55: =IF(AND(Q55<>"",Q55<=TODAY()),"Due","") | AW55: proprietary
A56: EBL-0055 | B56: Time-to-Close: Buyer Type vs Speed — Internal | C56: ka_pattern_V4G_Time_to_Close_BuyerType_Benelux_2026_v1 | D56: ka_pattern | E56: System | F56: V4G Internal | G56: internal | H56: dataset | I56: Cross-Sector | J56: Belgium; Benelux | K56: PE-backed; Corporate Buyer; Search Fund | L56: Deal Execution; Buyer Psychology; Pattern Detection | M56: 46128 | N56: 46128 | O56: 46128 | P56: quarterly | Q56: 46219 | R56: live | S56: high | T56: medium | U56: internal_only | V56: 5 | W56: 5 | X56: 5 | Y56: =V56+W56+X56 -> 15 | Z56: new | AA56: high | AB56: triage | AC56: Pattern; Internal Standard | AD56: FALSE | AE56: internal_only | AF56: internal | AG56: Analyst | AL56: attached | AM56: Dataset tracking time-to-close by buyer type: PE sponsor, corporate, family office, search fund. | AN56: Reveals buyer speed patterns — essential for competitive process design. | AO56: Buyer speed profiling, process optimization, competitive dynamics. | AP56: Very high — directly impacts process strategy and seller advice. | AQ56: Need segment by deal size band | AR56: TRUE | AS56: TRUE | AT56: TRUE | AU56: low | AV56: =IF(AND(Q56<>"",Q56<=TODAY()),"Due","") | AW56: proprietary
A57: EBL-0056 | B57: Clause Friction Register — Internal | C57: ka_failure_pattern_V4G_Clause_Friction_Benelux_2026_v1 | D57: ka_failure_pattern | E57: Failure | F57: V4G Internal | G57: internal | H57: sheet | I57: Cross-Sector | J57: Belgium; Benelux | K57: Founder-led; Family-owned; PE-backed | L57: Negotiation; Deal Execution; Failure Analysis | M57: 46128 | N57: 46128 | O57: 46128 | P57: monthly | Q57: 46158 | R57: live | S57: high | T57: medium | U57: internal_only | V57: 5 | W57: 5 | X57: 5 | Y57: =V57+W57+X57 -> 15 | Z57: new | AA57: high | AB57: triage | AC57: Failure Pattern; Internal Standard | AD57: FALSE | AE57: internal_only | AF57: internal | AG57: Partner | AL57: attached | AM57: Register of SPA/LOI clauses that consistently cause friction, delay, or deal collapse. | AN57: Maps where legal/commercial friction kills momentum — enables proactive clause management. | AO57: Clause taxonomy, friction frequency, resolution patterns. | AP57: Very high — directly prevents delays and builds legal process credibility. | AQ57: Need clause-level taxonomy with frequency counts | AR57: TRUE | AS57: TRUE | AT57: TRUE | AU57: low | AV57: =IF(AND(Q57<>"",Q57<=TODAY()),"Due","") | AW57: proprietary
A58: EBL-0057 | B58: Delay Source Mapping — Internal | C58: ka_failure_pattern_V4G_Delay_Source_Mapping_Benelux_2026_v1 | D58: ka_failure_pattern | E58: Failure | F58: V4G Internal | G58: internal | H58: memo | I58: Cross-Sector | J58: Belgium; Benelux | K58: Cross-sector | L58: Deal Execution; Failure Analysis; Pattern Detection | M58: 46128 | N58: 46128 | O58: 46128 | P58: monthly | Q58: 46158 | R58: live | S58: high | T58: medium | U58: internal_only | V58: 4 | W58: 5 | X58: 5 | Y58: =V58+W58+X58 -> 14 | Z58: new | AA58: high | AB58: triage | AC58: Failure Pattern; Pattern | AD58: FALSE | AE58: internal_only | AF58: internal | AG58: Editor | AL58: attached | AM58: Maps where delays originate in deal processes: legal, financial DD, management transition, regulatory. | AN58: Identifies systemic delay sources to build faster, more predictable processes. | AO58: Delay taxonomy, root cause analysis, process acceleration playbooks. | AP58: High — reduces process uncertainty and improves founder/buyer experience. | AQ58: Need map delays to responsible party (seller/buyer/advisor/legal) | AR58: TRUE | AS58: TRUE | AT58: TRUE | AU58: low | AV58: =IF(AND(Q58<>"",Q58<=TODAY()),"Due","") | AW58: proprietary
... A68: EBL-0067 | B68: Kahneman Applied: Deal Bias Playbook — Internal | C68: ka_pattern_V4G_Kahneman_Applied_Benelux_2026_v1 | D68: ka_pattern | E68: Patterns | F68: V4G Internal | G68: derived | H68: memo | I68: Cross-Sector | J68: Belgium; Benelux | K68: Founder-led; Family-owned; PE-backed; Corporate Buyer | L68: Buyer Psychology; Founder Psychology; Negotiation | M68: 46128 | N68: 46128 | O68: 46128 | P68: quarterly | Q68: 46219 | R68: live | S68: high | T68: medium | U68: internal_only | V68: 5 | W68: 5 | X68: 5 | Y68: =V68+W68+X68 -> 15 | Z68: new | AA68: high | AB68: triage | AC68: Pattern; Internal Standard; Editorial Angle | AD68: FALSE | AE68: internal_only | AF68: internal | AG68: Editor | AL68: attached | AM68: Applied playbook mapping Kahneman biases to specific deal phases: anchoring in pricing, loss aversion in sellers, framing in offers. | AN68: Bridges academic theory to practical deal execution — your observations + science. | AO68: Bias-per-phase mapping, intervention strategies, conversation scripts. | AP68: Very high — elevates every negotiation conversation. | AQ68: Need link to Kahneman framework (EBL-0061) + V4G casenotes | AR68: TRUE | AS68: TRUE | AT68: TRUE | AU68: low | AV68: =IF(AND(Q68<>"",Q68<=TODAY()),"Due","") | AW68: proprietary
A70: 📊 SUMMARY
A71: Library Category | B71: Count | D71: Asset Class | E71: Count | F71: %
A72: Core Market | B72: =COUNTIF(E2:E68,A72) -> 12 | D72: Commodity | E72: =COUNTIF(AW2:AW68,"commodity") -> 9 | F72: =IF(B82>0,E72/B82,0) -> 0.13432836
A73: Valuation & Capital | B73: =COUNTIF(E2:E68,A73) -> 9 | D73: Contextual | E73: =COUNTIF(AW2:AW68,"contextual") -> 21 | F73: =IF(B82>0,E73/B82,0) -> 0.31343284
A74: Playbooks | B74: =COUNTIF(E2:E68,A74) -> 7 | D74: Proprietary | E74: =COUNTIF(AW2:AW68,"proprietary") -> 37 | F74: =IF(B82>0,E74/B82,0) -> 0.55223881
A75: Sectors | B75: =COUNTIF(E2:E68,A75) -> 8 | D75: TOTAL | E75: =SUM(E72:E74) -> 67 | F75: =SUM(F72:F74) -> 1
A76: Investor Models | B76: =COUNTIF(E2:E68,A76) -> 6
A77: Macro | B77: =COUNTIF(E2:E68,A77) -> 5
A78: Editorial | B78: =COUNTIF(E2:E68,A78) -> 3
A79: Patterns | B79: =COUNTIF(E2:E68,A79) -> 6
A80: Failure | B80: =COUNTIF(E2:E68,A80) -> 5
A81: System | B81: =COUNTIF(E2:E68,A81) -> 6
A82: TOTAL | B82: =SUM(B72:B81) -> 67

Sheet Knowledge_Cards
A1: Card ID | B1: Source EBL | C1: Card Title | D1: Card Type | E1: Category | F1: Asset Class | G1: Key Insight | H1: Data Points | I1: So What? (Implication) | J1: Use In Conversation | K1: Linked Patterns | L1: Linked Theses | M1: Freshness | N1: Confidence | O1: Card Status | P1: Created
A2: KC-001 | B2: EBL-0005 | C2: Mid-Market Pricing Reality Check | D2: benchmark_extract | E2: Core Market | F2: contextual | G2: Benelux mid-market EV/EBITDA multiples are compressing — sellers anchored at 2021-22 peaks face 15-25% expectation gaps vs current market clearing prices. | H2: Median EV/EBITDA 6.0-7.5x (down from 8-9x peak); Healthcare/Tech premium 1.5-2x over industrials; <€10M EBITDA discount ~20% vs €10-50M; earn-out prevalence rising to ~40% of deals. | I2: Founders who waited 'for the right moment' since 2022 are now selling into a lower-multiple environment. The earn-out bridge is becoming standard, not exceptional. | J2: When a founder says 'my peer sold for 9x two years ago' — this card provides the market reality with specific data to recalibrate expectations without confrontation. | K2: Anchoring Bias in First Offers; Working Capital Shock at Closing | L2: Mid-Market Buyers Are Paying for Certainty, Not Just Growth | M2: current | N2: high | O2: active | P2: 46128
A3: KC-002 | B3: EBL-0001 | C3: Global PE: The Benelux Translation | D3: benchmark_extract | E3: Core Market | F3: contextual | G3: Global PE dry powder at record levels (~$2.5T) but deployment is slowing. For Benelux: PE buyers are pickier, processes longer, but willing to pay premium for 'deal certainty' sellers. | H3: Global PE AUM ~$8T; dry powder ~$2.5T; avg holding period extended to 5.5yr; exit volume down ~25% YoY; add-on share >50% of all PE deals; Benelux deal count stable but avg size declining. | I3: PE has the money but not the conviction. Sellers who present a 'zero-surprise' DD package and realistic pricing close faster and at better terms than those chasing top-of-range multiples. | J3: When a PE buyer says 'the market is tough' — counter with: dry powder is at record levels, the issue isn't capital availability but deployment confidence. Frame your client as the low-risk deployment. | K3: Buyer Withdrawal After LOI; Deal Failure at DD Phase | L3: Mid-Market Buyers Are Paying for Certainty, Not Just Growth | M3: current | N3: high | O3: active | P3: 46128
A4: KC-003 | B4: EBL-0013 | C4: House Valuation Anchors | D4: internal_standard | E4: Valuation & Capital | F4: contextual | G4: Five Damodaran reference points every V4G partner should know by heart — the numbers that frame any valuation conversation before a model is even opened. | H4: European equity risk premium: ~5.5%; small firm premium (SME): +2-3%; country risk premium Belgium: ~0.5%; unlevered beta range (services/manufacturing): 0.6-1.0; implied cost of equity for typical Benelux SME: 12-15%. | I4: When founders quote '8x EBITDA' from a newspaper headline, these numbers translate that into what a buyer's DCF actually says. The gap between headline multiples and risk-adjusted returns is where negotiation happens. | J4: Never argue multiples — argue cost of equity. 'At your asking price, a buyer's implied return is 7%. Their fund targets 20%. Let me show you why 6.5x is actually a strong offer.' | K4: Anchoring Bias in First Offers; Price vs Certainty Trade-Off | L4: Behavioral Biases Are the Hidden Deal Variable | M4: current | N4: high | O4: active | P4: 46128
A5: KC-004 | B5: EBL-0049 | C5: Founder Hesitation Playbook | D5: pattern_card | E5: Patterns | F5: proprietary | G5: Founders hesitate at 3 predictable phases: pre-mandate (identity crisis), post-LOI (seller's remorse), pre-closing (last-minute doubt). Each phase requires a different intervention. | H5: Phase 1 triggers: legacy anxiety, 'not the right time' loop, advisor shopping; Phase 2 triggers: price re-anchoring, employee guilt, family pressure; Phase 3 triggers: tax shock, earn-out fear, loss of control panic. | I5: Most deal failures attributed to 'cold feet' are actually predictable phase-specific reactions. Knowing which phase the founder is in determines whether you reassure, reframe, or accelerate. | J5: When a founder goes silent post-LOI: don't chase with deal updates. Instead, address the underlying emotion: 'Many founders feel this way at this stage. It's not doubt about the deal — it's grief about the transition.' | K5: Founder Hesitation Before LOI; Anchoring Bias in First Offers; Buyer Withdrawal After LOI | L5: Behavioral Biases Are the Hidden Deal Variable; Deal Failures Are Predictable — And Preventable | M5: evergreen | N5: medium | O5: active | P5: 46128
A6: KC-005 | B6: EBL-0048 | C6: Buyer Conviction Signals | D6: pattern_card | E6: Patterns | F6: proprietary | G6: Buyer seriousness can be read from 4 signals within the first 2 weeks: response speed, question quality, internal team deployment, and reference to integration planning. | H6: Signal 1: <48hr response = serious, >5 days = tourist; Signal 2: operational questions > financial questions = real buyer; Signal 3: CFO/COO involvement early = conviction; Signal 4: mentions of integration timeline = closing intent. | I6: Stop wasting time on 'interested' buyers who are actually benchmarking. These 4 signals let you rank buyer conviction in week 2 instead of week 12. | J6: When presenting a buyer shortlist to a founder: 'Based on early signals, Buyer A and C show real conviction — here's specifically why. Buyer B is likely benchmarking. I recommend focusing our management presentations on A and C.' | K6: Buyer Withdrawal After LOI; Hiring Surge as Acquisition Signal | L6: Signal Convergence Predicts Deal Activity | M6: evergreen | N6: medium | O6: active | P6: 46128
A7: KC-006 | B7: EBL-0018 | C7: Vendor Loan Intelligence | D7: internal_standard | E7: Valuation & Capital | F7: proprietary | G7: Vendor loans are the hidden bridge between seller expectations and buyer affordability — used in ~30% of mid-market deals, but poorly understood by most founders. | H7: Typical range: 10-25% of EV; duration: 3-5 years; interest: 3-5% above base; subordination: always behind senior debt; key negotiation: security vs unsecured; market trend: increasing as bank leverage tightens. | I7: Founders who understand vendor loans before negotiations start accept them as a strategic tool rather than a sign of buyer weakness. This shifts the conversation from 'he can't afford it' to 'this protects my upside.' | J7: When structuring a deal with a gap: 'A vendor loan of 15% isn't the buyer saying they can't pay — it's you retaining skin in the game during the transition. At 4% interest, it's better than most fixed-income investments.' | K7: Working Capital Shock at Closing; Clause Friction on Earn-Out Terms | L7: Mid-Market Buyers Are Paying for Certainty, Not Just Growth | M7: evergreen | N7: high | O7: active | P7: 46128
A8: KC-007 | B8: EBL-0037 | C8: Platform vs Add-On Decision Tree | D8: pattern_card | E8: Investor Models | F8: proprietary | G8: PE buyers evaluate targets through two lenses — platform (standalone leadership) or add-on (bolt-on to existing portfolio). The lens determines valuation, process speed, and negotiation dynamics. | H8: Platform criteria: >€5M EBITDA, management depth, market position, standalone scalability; Add-on criteria: strategic fit > financials, faster process, lower multiples (0.5-1.5x discount), integration synergies valued; Hybrid: increasingly common in Benelux. | I8: Positioning a client as 'platform-worthy' vs accepting add-on classification changes the expected multiple by 1-2x EBITDA. This is often a €2-5M difference on a mid-market deal. | J8: When a PE buyer offers add-on multiples for a platform-quality business: 'This company has 3 of the 4 platform characteristics your fund typically targets. The add-on discount doesn't reflect the standalone management depth and market position.' | K8: Sponsor-to-Sponsor Transaction Patterns; Hold Period by Fund Type | L8: Mid-Market Buyers Are Paying for Certainty, Not Just Growth | M8: evergreen | N8: high | O8: active | P8: 46128
A9: KC-008 | B9: EBL-0015 | C9: Private vs Public Pricing Gap | D9: benchmark_extract | E9: Valuation & Capital | F9: contextual | G9: Private market multiples lag public markets by 6-12 months. Current Lincoln data shows private multiples still adjusting while public markets have partially recovered — creating a temporary arbitrage window. | H9: Lincoln PMI private multiples: ~7.5x mid-market (Q1 2026); public comparables trading at 9-11x; lag typically closes within 2-3 quarters; sector dispersion widening: tech/healthcare 9-10x private vs industrials 5.5-6.5x. | I9: For sellers: 'wait for recovery' may mean 6+ more months. For PE buyers: current private pricing represents a value window before public-to-private convergence. The smart money is deploying now, not waiting. | J9: When a buyer argues multiples are too high: 'Lincoln data shows private multiples are still 20-25% below public comparables. This isn't expensive — this is the lag closing. In 2-3 quarters, you'll wish you'd moved faster.' | K9: Anchoring Bias in First Offers | L9: Mid-Market Buyers Are Paying for Certainty, Not Just Growth | M9: current | N9: high | O9: active | P9: 46128
A10: KC-009 | B10: EBL-0009 | C10: Belux M&A Landscape Card | D10: benchmark_extract | E10: Core Market | F10: contextual | G10: Belux M&A market is structurally different from NL/DACH: smaller deal sizes, higher succession-driven share, stronger family attachment, and fewer professional intermediaries. | H10: Annual deal count Belgium: ~350-400 (vs NL: ~600-700); succession-driven: ~55% of Belgian deals vs ~35% in NL; avg deal size €5-15M; PE share growing but still <40% of deals; Wallonia significantly underserved. | I10: The Belgian market rewards patience and trust over process efficiency. Founders here choose advisors they like over advisors who promise the highest price. Relationship-first positioning wins. | J10: When pitching a Belgian founder: 'The Vlerick data shows that 55% of Belgian transactions are succession-driven. Your situation is typical, not exceptional. Here's what successful transitions look like in your sector.' | K10: Founder Hesitation Before LOI; CFO Change as Sale Trigger | L10: Signal Convergence Predicts Deal Activity | M10: current | N10: high | O10: active | P10: 46128
A11: KC-010 | B11: EBL-0051 | C11: Why Deals Die — The Top 5 | D11: failure_card | E11: Failure | F11: proprietary | G11: 80% of mid-market deal failures trace back to 5 root causes. Most are preventable if identified before LOI stage. The single biggest killer isn't price disagreement — it's information asymmetry during DD. | H11: #1: DD surprises (35% of failures) — undisclosed risks surface; #2: Founder cold feet (25%) — hesitation post-LOI; #3: Price re-trading (20%) — buyer adjusts after DD; #4: Financing collapse (12%) — bank/fund pullback; #5: Regulatory/structural (8%). | I11: Deal failure is not random. Pre-DD readiness investment and founder expectation management at mandate stage eliminate the top 2 causes (60% of all failures). This is the highest-ROI activity in M&A advisory. | J11: When onboarding a new mandate: 'Based on our deal failure analysis, the #1 risk isn't finding a buyer — it's DD surprises. Let me walk you through our pre-DD readiness checklist. 30 minutes now saves 6 months later.' | K11: Deal Failure at DD Phase; Buyer Withdrawal After LOI; Working Capital Shock at Closing; Founder Hesitation Before LOI | L11: Deal Failures Are Predictable — And Preventable | M11: evergreen | N11: high | O11: active | P11: 46128

Sheet Source_Register
A1: Source Name | B1: Source Category | C1: Reliability | D1: Coverage | E1: Typical Cadence | F1: Paid / Free | G1: Default Freshness | H1: Source URL | I1: Notes
A2: Bain & Company | B2: consulting | C2: high | D2: global; europe; private-equity | E2: annual | F2: free | G2: recent | H2: https://www.bain.com/ | I2: Core PE benchmark source
A3: PitchBook | B3: data_provider | C3: high | D3: global; europe; private-equity; valuation | E3: quarterly | F3: paid | G3: recent | H3: https://pitchbook.com/ | I3: Valuation and dealflow data
A4: Argos Wityu | B4: advisory_firm | C4: high | D4: europe; mid-market | E4: quarterly | F4: free | G4: recent | H4: https://argos.wityu.fund/ | I4: Mid-market index reference
A5: Clearwater International | B5: advisory_firm | C5: high | D5: europe; benelux; sector-specific | E5: quarterly | F5: free | G5: recent | H5: https://www.clearwaterinternational.com/ | I5: Mid-market monitor and sector reports
A6: Vlerick | B6: academic | C6: high | D6: belgium; benelux | E6: annual | F6: mixed | G6: recent | H6: https://www.vlerick.com/ | I6: Belux relevance
A7: Lincoln International | B7: advisory_firm | C7: high | D7: global; valuation; private-equity | E7: quarterly | F7: free | G7: recent | H7: https://www.lincolninternational.com/ | I7: Private market index
A8: BDO | B8: consulting | C8: medium | D8: global; private-equity | E8: annual | F8: free | G8: recent | H8: https://www.bdo.global/ | I8: PE sentiment
A9: McKinsey | B9: consulting | C9: high | D9: global; private-equity | E9: annual | F9: free | G9: recent | H9: https://www.mckinsey.com/ | I9: Private markets review
A10: Invest Europe | B10: proprietary | C10: high | D10: europe; private-equity | E10: annual | F10: mixed | G10: recent | H10: https://www.investeurope.eu/ | I10: European activity data
A11: Rabobank | B11: bank | C11: high | D11: europe; food & agri | E11: annual | F11: mixed | G11: recent | H11: https://www.rabobank.com/ | I11: Food & agri intelligence
A12: DC Advisory | B12: advisory_firm | C12: medium | D12: europe; healthcare | E12: annual | F12: free | G12: recent | H12: https://www.dcaadvisory.com/ | I12: Healthcare sector review
... A22: Dealflow.news | B22: media | C22: medium | D22: benelux; m&a; editorial | E22: weekly | F22: internal | G22: live | H22: https://dealflow.news/ | I22: Editorial reuse source
A23: V4G Internal | B23: internal | C23: high | D23: internal; proprietary | E23: ad_hoc | F23: internal | G23: live | I23: Internal standards, patterns, case notes
A24: Partner Insight | B24: partner_input | C24: medium | D24: internal; proprietary | E24: ad_hoc | F24: internal | G24: live | I24: Partner notes and hypotheses
A25: Daniel Kahneman | B25: academic | C25: high | D25: global; behavioral-economics; psychology | E25: reference | F25: free | G25: reference | I25: Prospect theory, anchoring, loss aversion — behavioral science applied to deal psychology
A26: V4G Case Archive | B26: internal | C26: high | D26: internal; proprietary; deal-execution | E26: ad_hoc | F26: internal | G26: live | I26: Internal deal case archive — raw material for pattern, failure, and signal extraction

Sheet Pattern_Register
A1: Pattern Name | B1: Pattern Type | C1: Status | D1: Confidence | E1: Sector | F1: Geography | G1: First Seen | H1: Last Seen | I1: Frequency 90D | J1: Editorial Relevance | K1: Commercial Relevance | L1: Description | M1: Observable Signals | N1: Deal Implication | O1: Buyer / Founder Relevance | P1: Linked Library Item IDs | Q1: Pattern Owner | R1: Review Cadence | S1: Next Review Date | T1: Needs Update
A2: Founder Hesitation Before LOI | B2: behavioral | C2: emerging | D2: medium | E2: Cross-Sector | F2: Belgium; Benelux | G2: 46128 | H2: 46128 | I2: 1 | J2: 5 | K2: 5 | L2: Founder momentum slows just before formal commitment despite strong process logic. | M2: Longer response times; softer language; repeated timing objections; renewed identity concerns. | N2: Can delay or derail process unless certainty and role transition are managed. | O2: High relevance for founder-led sell-side mandates. | P2: EBL-0046; EBL-0049; EBL-0065 | Q2: Editor | R2: monthly | S2: 46158 | T2: FALSE
A3: Deal Failure at DD Phase | B3: failure | C3: emerging | D3: medium | E3: Cross-Sector | F3: Belgium; Benelux | G3: 46128 | H3: 46128 | I3: 1 | J3: 5 | K3: 5 | L3: Disproportionate number of deal failures occur during DD phase — driven by preparation gaps and information asymmetry. | M3: Extended DD timelines; repeated information requests; advisor frustration signals; buyer re-pricing. | N3: Process can be saved by pre-DD readiness investment and managed expectation setting. | O3: High relevance for both sell-side preparation and buyer process evaluation. | P3: EBL-0051; EBL-0053; EBL-0027 | Q3: Editor | R3: monthly | S3: 46158 | T3: FALSE
A4: Buyer Withdrawal After LOI | B4: failure | C4: emerging | D4: low | E4: Cross-Sector | F4: Belgium; Benelux | G4: 46128 | H4: 46128 | I4: 1 | J4: 5 | K4: 5 | L4: Buyers withdraw post-LOI more often than expected — triggered by DD surprises, market shifts, or internal priority changes. | M4: Slower communication; narrowing DD scope; increased legal friction; delayed management meetings. | N4: Need backup buyer strategy and faster LOI-to-close execution. | O4: Critical for managing seller expectations and process risk. | P4: EBL-0051; EBL-0052; EBL-0056 | Q4: Partner | R4: monthly | S4: 46158 | T4: FALSE
A5: Clause Friction on Earn-Out Terms | B5: execution | C5: emerging | D5: medium | E5: Cross-Sector | F5: Belgium; Benelux | G5: 46128 | H5: 46128 | I5: 1 | J5: 4 | K5: 5 | L5: Earn-out clause definitions consistently cause friction — measurement periods, targets, and control rights are the top 3 blockers. | M5: Extended SPA negotiation; earn-out clause redlines exceeding 3 rounds; founder frustration spikes. | N5: Pre-agreed earn-out frameworks dramatically reduce closing friction. | O5: Very high for founders with significant earn-out components. | P5: EBL-0019; EBL-0056; EBL-0050 | Q5: Partner | R5: monthly | S5: 46158 | T5: FALSE
A6: Anchoring Bias in First Offers | B6: behavioral | C6: emerging | D6: medium | E6: Cross-Sector | F6: Global | G6: 46128 | H6: 46128 | I6: 1 | J6: 5 | K6: 5 | L6: First price indication anchors the entire negotiation — founders who set high initial expectations struggle to accept realistic market pricing. | M6: Founder references to 'comparable' transactions; repeated upward price revisions; delayed market testing. | N6: Professional valuation framing at mandate stage prevents anchoring damage. | O6: Universal — affects every sell-side engagement. | P6: EBL-0061; EBL-0067; EBL-0049 | Q6: Editor | R6: quarterly | S6: 46219 | T6: FALSE
A7: Hiring Surge as Acquisition Signal | B7: strategic | C7: emerging | D7: low | E7: Cross-Sector | F7: Belgium; Benelux | G7: 46128 | H7: 46128 | I7: 0 | J7: 4 | K7: 5 | L7: Companies hiring aggressively in specific functions (corp dev, integration) often precede acquisitions within 6-12 months. | M7: LinkedIn job postings in M&A/integration roles; new corp dev hires; BD team expansion. | N7: Early buyer identification for competitive sell-side processes. | O7: High for proactive buyer mapping and origination. | P7: EBL-0058; EBL-0060 | Q7: Analyst | R7: weekly | S7: 46135 | T7: FALSE
A8: CFO Change as Sale Trigger | B8: strategic | C8: emerging | D8: low | E8: Cross-Sector | F8: Belgium; Benelux | G8: 46128 | H8: 46128 | I8: 0 | J8: 5 | K8: 5 | L8: CFO departures or appointments in founder-led companies often precede sale processes within 12-18 months. | M8: CFO resignation; external CFO appointment; increased accountant/advisor engagement. | N8: Timing signal for outreach — founder is likely preparing for transaction. | O8: Very high for sell-side origination targeting. | P8: EBL-0059; EBL-0060 | Q8: Analyst | R8: weekly | S8: 46135 | T8: FALSE
A9: Working Capital Shock at Closing | B9: execution | C9: emerging | D9: medium | E9: Cross-Sector | F9: Belgium; Benelux | G9: 46128 | H9: 46128 | I9: 1 | J9: 5 | K9: 5 | L9: Working capital adjustment mechanisms consistently surprise sellers at closing — creates trust damage and delays. | M9: Closing balance disputes; locked box vs completion accounts friction; seller shock at final price. | N9: Early education on WC mechanisms prevents closing-stage explosions. | O9: Critical for founder-led sell-side mandates. | P9: EBL-0021; EBL-0056; EBL-0057 | Q9: Partner | R9: monthly | S9: 46158 | T9: FALSE

Sheet Thesis_Register
A1: Thesis Title | B1: Thesis Type | C1: Status | D1: Core Claim | E1: Why It Matters | F1: Supporting Evidence | G1: Counterpoints | H1: Linked Patterns | I1: Linked Library Item IDs | J1: Owner | K1: Confidence | L1: Audience | M1: Publication Potential | N1: Next Review Date
A2: Mid-Market Buyers Are Paying for Certainty, Not Just Growth | B2: valuation | C2: idea | D2: In the current market, process certainty and clean execution increasingly outweigh pure top-line growth in buyer willingness to pay. | E2: Useful for editorial positioning and founder conversations about preparation quality. | F2: Combine benchmarks, internal case notes, and working capital friction patterns. | G2: Some sectors still price aggressively for growth alone. | H2: Founder Hesitation Before LOI; Working Capital Shock at Closing | I2: EBL-0001; EBL-0013; EBL-0018 | J2: Editor | K2: medium | L2: founders; buyers; investors | M2: high | N2: 46219
A3: Deal Failures Are Predictable — And Preventable | B3: editorial | C3: idea | D3: Most deal failures follow identifiable patterns that can be detected early and mitigated through systematic process management. | E3: Builds Grapevine’s core editorial IP: nobody else publishes failure intelligence. Creates defensible thought leadership. | F3: Combine failure case register, phase failure analysis, and DD friction data. | G3: Small sample size initially; some failures are genuinely unpredictable. | H3: Deal Failure at DD Phase; Buyer Withdrawal After LOI; Working Capital Shock at Closing | I3: EBL-0051; EBL-0052; EBL-0053; EBL-0027 | J3: Editor | K3: medium | L3: founders; advisors; PE buyers | M3: high | N3: 46219
A4: Signal Convergence Predicts Deal Activity | B4: strategic | C4: idea | D4: Multiple weak signals (hiring patterns, leadership changes, sector pressure) converging on a single target predict deal activity 6-18 months ahead. | E4: Enables proactive origination instead of reactive deal-chasing. Transforms Grapevine from newsletter to intelligence platform. | F4: Map hiring signals, CFO changes, and sector dynamics to confirmed deal outcomes. | G4: Correlation ≠ causation; signals may produce false positives; small dataset risk. | H4: Hiring Surge as Acquisition Signal; CFO Change as Sale Trigger | I4: EBL-0058; EBL-0059; EBL-0060 | J4: Editor | K4: low | L4: PE buyers; corporate development; advisors | M4: high | N4: 46219
A5: Behavioral Biases Are the Hidden Deal Variable | B5: editorial | C5: idea | D5: Cognitive biases (anchoring, loss aversion, framing) systematically distort founder and buyer decisions at predictable deal phases. | E5: Elevates M&A advice from commercial intuition to behavioral science. Unique editorial angle for Dealflow.news. | F5: Map Kahneman framework to V4G deal observations and casenotes. | G5: Academic theory may oversimplify deal-specific emotional dynamics. | H5: Anchoring Bias in First Offers; Founder Hesitation Before LOI | I5: EBL-0061; EBL-0067; EBL-0049; EBL-0065 | J5: Editor | K5: medium | L5: founders; advisors; editorial audience | M5: high | N5: 46219

Sheet Update_Timetable
A1: KA Type | B1: Default Cadence | C1: Typical Owner | D1: Review Trigger | E1: Recommended Action | F1: Next Review Rule
A2: ka_signal_digest | B2: weekly | C2: Editor / Analyst | D2: Every week | E2: Refresh signals and archive stale items | F2: +7 days
A3: ka_benchmark | B3: quarterly | C3: Analyst | D3: Quarterly or new edition | E3: Update benchmark record and compare with prior version | F3: +3 months
A4: ka_market_map | B4: quarterly | C4: Analyst / Sector lead | D4: Quarterly or new report | E4: Refresh sector maps, pricing, consolidation notes | F4: +3 months
A5: ka_framework | B5: annual | C5: Editor | D5: Annual or new edition | E5: Check whether framework still reflects market practice | F5: +12 months
A6: ka_pattern | B6: monthly | C6: Editor / Partner | D6: Monthly | E6: Validate pattern recurrence and link new supporting items | F6: +1 month
A7: ka_failure_pattern | B7: monthly | C7: Editor / Partner | D7: Monthly / after failed process | E7: Log failure factors and early-warning signals | F7: +1 month
A8: ka_thesis | B8: quarterly | C8: Editor | D8: Quarterly | E8: Reassess claim strength, evidence and publication potential | F8: +3 months
A9: ka_editorial_angle | B9: weekly | C9: Editor | D9: Weekly | E9: Promote, merge, or archive angles based on market relevance | F9: +7 days
A10: ka_internal_standard | B10: quarterly | C10: Partner / Editor | D10: Quarterly | E10: Refresh house view and norms | F10: +3 months
A11: ka_library_source | B11: annual | C11: Analyst | D11: Annual | E11: Verify if source remains core and active | F11: +12 months

Sheet Controlled_Values
A1: KA Type | B1: Library Category | C1: Source Type | D1: Asset Format | E1: Freshness Class | F1: Confidence | G1: Evidence Status | H1: Priority | I1: Editorial Status | J1: Publishing Relevance | K1: Sensitivity | L1: Update Cadence | M1: Pattern Type | N1: Pattern Status | O1: Thesis Type | P1: Thesis Status | Q1: Source Category | R1: Reliability | S1: Paid/Free | T1: Company Relevance | U1: Time Sensitivity | V1: Asset Class | W1: Novelty | X1: Card Type | Y1: Card Status
A2: ka_benchmark | B2: Core Market | C2: external | D2: pdf | E2: live | F2: high | G2: single_source | H2: high | I2: backlog | J2: high | K2: public | L2: daily | M2: strategic | N2: emerging | O2: editorial | P2: idea | Q2: advisory_firm | R2: high | S2: paid | T2: Founder-led | U2: high | V2: commodity | W2: new | X2: benchmark_extract | Y2: active
A3: ka_market_map | B3: Valuation & Capital | C3: internal | D3: doc | E3: recent | F3: medium | G3: multi_source | H3: medium | I3: triage | J3: medium | K3: internal | L3: weekly | M3: behavioral | N3: active | O3: sector | P3: building | Q3: academic | R3: medium | S3: free | T3: Family-owned | U3: medium | V3: contextual | W3: contextual | X3: pattern_card | Y3: draft
A4: ka_pattern | B4: Playbooks | C4: derived | D4: note | E4: reference | F4: low | G4: internal_only | H4: low | I4: validated | J4: low | K4: restricted | L4: monthly | M4: valuation | N4: validated | O4: macro | P4: supported | Q4: bank | R4: low | S4: internal | T4: PE-backed | U4: low | V4: proprietary | W4: known_pattern | X4: internal_standard | Y4: archived
A5: ka_failure_pattern | B5: Sectors | C5: mixed | D5: sheet | E5: archive | F5: unknown | G5: sensitive | I5: converted | J5: internal_only | K5: sensitive | L5: quarterly | M5: execution | N5: declining | O5: valuation | P5: published | Q5: internal | S5: mixed | T5: Search Fund | U5: timeless | W5: emerging | X5: failure_card | Y5: superseded
A6: ka_framework | B6: Investor Models | D6: slide | G6: unverified | I6: published | L6: annual | M6: failure | N6: archived | O6: succession | P6: archived | Q6: media | T6: Corporate Buyer | X6: thesis_card
A7: ka_thesis | B7: Macro | D7: link | I7: archived | L7: ad_hoc | M7: sector | O7: investor | Q7: newsletter | T7: Independent SME | X7: signal_card
A8: ka_editorial_angle | B8: Editorial | D8: article | M8: investor | O8: strategic | Q8: data_provider | T8: Buy-and-Build Platform
A9: ka_signal_digest | B9: Patterns | D9: dataset | M9: succession | Q9: regulator | T9: Add-on Target
A10: ka_internal_standard | B10: Failure | D10: memo | Q10: consulting | T10: Succession Situation
A11: ka_library_source | B11: System | D11: bundle | Q11: partner_input | T11: Cross-sector
Q12: proprietary
